Workbook

Sheet Base 3F
A1: F | B1: Cantidad de Empresas: --> | C1: =COUNTA(B5:B3164) -> 2175 | S1: =COUNTA(S5:S2041) -> 1875 | T1: =COUNTA(T5:T2041) -> 1640 | U1: =COUNTA(U5:U2041) -> 1481 | V1: =COUNTIFS(V5:V1956,"<>No encontrado / No tiene",V5:V1956,"<>") -> 984
A2: =COUNTIF(A5:A1968, "C") -> 1219 | B2: Contador de filas con info (C) -> tiene mail y tel - minimo 1 de c/u. | D2: Datos de la organización | O2: Datos de contacto
A3: =COUNTIF(A5:A1968, "F") -> 741 | B3: Contador de filas con falta de info (F) -> tiene mail o tel. | E3: Dirección | O3: Contacto 1 | Q3: Contacto 2 | S3: Datos generales | Z3: Observaciones / Comentario
B4: Razón Social AFIP | C4: CUIT AFIP | D4: Tipos de Organizacion | E4: Calle | F4: Número | G4: Localidad | H4: C.P. | I4: Cod. Actividad | J4: Rubro | K4: Actividad | L4: Tipo de Producto | M4: Productos Principales | N4: Cant. de empleados | O4: Nombre y apellido | P4: Celular | Q4: Nombre y apellido | R4: Celular | S4: Teléfono A | T4: Teléfono B | U4: Teléfono C | V4: Web / Instagram | W4: Importa | X4: Exporta | Y4: Activa
A5: C | B5: 1989 ESTUDIO A S.R.L. | ALEJANDRO Y MIGUEL ANGEL RIZZI S.H. | C5: 30709328995 | 30710682816 | D5: Empresa | E5: Cnel. Pringles | F5: 3552 | G5: Caseros | H5: 1678 | I5: 162909 | J5: Papel | K5: Fabricación de artículos de papel y cartón N.C.P. | L5: B2C | N5: 16 | O5: Angelina Muñoz | P5: 11 4424-3309 | S5: 11 4734-2356 | T5: 11 4716-1699 | V5: http://www.estudioapop.com.ar/ | W5: No | X5: No | Y5: Si
A6: C | B6: 2G ADHESIVOS S.R.L. | C6: 30714815179 | D6: Empresa | E6: Puan | F6: 4523 | G6: Caseros | H6: 1678 | I6: 202907 | J6: Química | K6: Fabricación de colas, adhesivos, aprestos y cementos excepto los odontológicos obtenidos de sustancias minerales y vegetales | N6: 0 | O6: Gabriel | P6: 15 5734-1450 | S6: 11 5734-1450 | T6: 11 4759-8416 | V6: https://www.dosg.com.ar/ | W6: No | X6: No | Y6: Si
A7: C | B7: A D S.A. | C7: 30710393725 | D7: Empresa | E7: Escultor Santiago Parodi | F7: 5028 | G7: Caseros | H7: 1678 | I7: 310020 | J7: Metalúrgica | K7: Fabricación de muebles y partes de muebles, excepto de madera | L7: B2B, B2C | M7: Muebles, exhibidores | N7: 22 | O7: Leandro Greco | S7: 11 4759-4142 | T7: 4115-4774 | V7: https://amasd.com.ar/ | W7: No | X7: No | Y7: Si
A8: C | B8: A PATKO Y CIA S.A. | C8: 30518263834 | D8: Empresa | E8: Trenque Lauquen | F8: 4749 | G8: Caseros | H8: 1678 | I8: 293090 | J8: Metalúrgica | K8: Fabricación de partes, piezas y accesorios para vehículos automotores y sus motores N.C.P. | N8: 4 | O8: Cristian Patko | S8: 11 4750-2658 | T8: 11 4750-5929 | V8: No encontrado / No tiene | W8: Si | X8: No | Y8: Si
A9: F | B9: A T G S.R.L. | C9: 30611422268 | D9: Empresa | E9: Av. Maipú | F9: 4381 | G9: Ciudadela | H9: 1702 | I9: 281102 | J9: Metalúrgica | K9: Fabricación de Estructuras Metálicas para la Construcción | L9: B2B | N9: 0 | S9: 4635-3692 | T9: 4488-1753 | V9: No encontrado / No tiene | W9: No | X9: No | Y9: Si
A10: F | B10: A V C S.R.L. | C10: 30662138157 | D10: Empresa | E10: Av. Rivadavia | F10: 12110 | G10: Ciudadela | H10: 1702 | I10: 801090 | J10: Servicios | K10: Servicios de seguridad e investigación N.C.P. | N10: 17 | S10: 4488-2330 | V10: No encontrado / No tiene | W10: No | X10: No | Y10: Si
A11: C | B11: A VALGO S.R.L. | C11: 30701156532 | D11: Empresa | E11: Gral. Roca | F11: 3397 | G11: Ciudadela | H11: 1704 | I11: 812090 | J11: Servicios | K11: Servicios de limpieza N.C.P. | N11: 11 | S11: 11 5307-2333 | T11: 4653-2507 | V11: https://valgo.com.ar/ | W11: No | X11: No | Y11: Si
A12: C | B12: AANTAJ S.R.L. | C12: 30709992178 | D12: Empresa | E12: Zapiola | F12: 21 | G12: Ciudadela | H12: 1702 | I12: 139209 | J12: Textil | K12: Fabricación de artículos confeccionados de materiales textiles N.C.P., excepto prendas de vestir | L12: B2B, B2C | N12: 4 | S12: 11 5290-7165 | T12: 4460-5957 | U12: 4650-2340 | V12: http://www.aantaj.com.ar/ | W12: Si | X12: Si | Y12: Si
A13: C | B13: ABAFLEX S.A. | C13: 30597429130 | D13: Empresa | E13: Chubut | F13: 4352 | G13: Ciudadela | H13: 1702 | I13: 222090 | J13: Plástica | K13: Fabricación de productos plásticos en formas básicas y artículos de plástico N.C.P., excepto muebles | L13: B2B | N13: 14 | S13: 4657-6800 | T13: 4657-4846 | V13: www.abaflex.com.ar | W13: Si | X13: Si | Y13: Si
A14: C | B14: ABASTECEDORA DEL OESTE S.R.L.E.F. | C14: 30647487285 | D14: Empresa | E14: Félix Ballester | F14: 262 | G14: Ciudadela | H14: 1702 | I14: 383961 | J14: Electrónica | K14: Fabricación de aparatos y suministros eléctricos no clasificados en otra parte | N14: 0 | S14: 4653 5026 | T14: 4657 0355 | V14: No encontrado / No tiene | W14: No | X14: No | Y14: Si
A15: C | B15: ABBOMAR S.A. | C15: 30710802552 | D15: Empresa | E15: Raúl Scalabrini Ortiz | F15: 2945 | G15: Caseros | H15: 1678 | I15: 433010 | J15: Construcción | K15: Instalaciones de carpintería, herrería de obra y artística (Incluye instalación de puertas y ventanas, carpintería metálica y no metálica, etc.) | L15: B2C | N15: 6 | S15: 15 5101-3019 | T15: 4843-9243 | U15: 11 5101-3019 | V15: http://www.abbomar.com/contacto | W15: No | X15: No | Y15: Si
A16: C | B16: ABELARDO ESTEBAN (VALVULAS ESTEBAN) | C16: 20105339330 | D16: Persona Física | E16: Constancia | F16: 1130 | G16: Ciudadela | H16: 1702 | I16: 259993 | J16: Metalúrgica | K16: Fabricación de productos metálicos de tornería y/o matricería | O16: Lilia Pardo? (Gestora?) | S16: 4653-0950 | T16: 4657-8146 | V16: https://valvulas-esteban.com.ar/
A17: C | B17: ABERMATIC S.R.L. | C17: 30707243844 | D17: Empresa | E17: Santiago Bonifacini | F17: 5337 | G17: Caseros | H17: 1678 | I17: 271010 | J17: Metalúrgica | K17: Fabricación de motores, generadores y transformadores eléctricos | L17: B2B, BK | N17: 30 | O17: Sandro Vivaldi (Socio gerente) | S17: 4750-5309 | T17: 4750-3952 | U17: 4750-3233 | V17: www.abermatic.com | W17: Si | X17: Si | Y17: Si
A18: F | B18: ABIS S.R.L. | C18: 30663783013 | D18: Empresa | E18: Marco Polo | F18: 5157 | G18: Villa Bosch | H18: 1682 | I18: 452900 | J18: Construcción | K18: Obras de ingeniería civil N.C.P. | L18: B2B | N18: 0 | S18: 4743-7245 | V18: No encontrado / No tiene | W18: No | X18: No | Y18: Si
A19: C | B19: ABK SOCIEDAD DE RESPONSABILIDAD LIMITADA | C19: 33625752499 | D19: Empresa | E19: Dr. José Rebizzo | F19: 5683 | G19: Caseros | H19: 1678 | I19: 202907 | J19: Química | K19: Fabricación de colas, adhesivos, aprestos y cementos excepto los odontológicos obtenidos de sustancias minerales y vegetales | N19: 10 | P19: 11 4750-2910 | S19: 11 3518-7549 | T19: 11 4750-2910 | U19: 4734-2170 | V19: https://www.abk.com.ar/ | W19: Si | X19: Si | Y19: Si
A20: F | B20: ACABADOS NEWTON S.R.L. | C20: 30714258377 | D20: Empresa | E20: General Villegas | F20: 5236 | G20: Caseros | H20: 1678 | I20: 329090 | J20: Metalúrgica | K20: Tratamiento y acabado de superficies como herrajes para muebles y obra, ferretería, cortinería, burlonería, bisagras, etc | N20: 4 | S20: 4115-7357/57 | T20: 4658-7386 | V20: http://www.acabadosnewton.com.ar/ | W20: No | X20: No | Y20: Si
A21: C | B21: ACCECUER S.A. | C21: 30632566448 | D21: Empresa | E21: Juan Zanella | F21: 4656 | G21: Caseros | H21: 1678 | I21: 151200 | J21: Cuero | K21: Fabricación de maletas, bolsos de mano y similares, artículos de talabartería y artículos de cuero N.C.P. | L21: B2B, B2C | M21: Manufactura de cinturones de cuero y artículos de marroquinería | N21: 23 | S21: 11 2280 1856 | T21: 5293-0118 | U21: 4541-3222 | V21: http://www.accecuer.com.ar/ | W21: Si | X21: Si | Y21: Si
A22: C | B22: ACEROS ACEPER DE DALL ASTA CLAUDIA VIVIANA | C22: 27162030618 | D22: Persona Física | E22: Esteban Merlo | F22: 4369 | G22: Caseros | H22: 1678 | I22: 475290 | J22: Construcción | K22: Venta al por menor de materiales de construcción | S22: 4115-6713 | T22: 4750-6996 | U22: 1140376715 | V22: http://acerosaceper.com.ar/
A23: C | B23: ACEROS COFER S.A. | C23: 30707576444 | D23: Empresa | E23: Av. Pres. Juan Domingo Perón | F23: 8299 | G23: Pablo Podestá | H23: 1657 | I23: 259999 | J23: Metalúrgica | K23: Fabricación de productos elaborados de metal N.C.P. | L23: B2B | N23: 31 | O23: Juan Carlos Luna | Q23: Fabian Fernandez Crasso | R23: 15 3210-1300 | 15 7163-0905 | S23: 4848-1010 | 4848-4140 | T23: 4848-3300 | U23: 4848-1600 | V23: https://www.aceroscofer.com.ar/ | W23: Si | X23: Si | Y23: Si
A24: C | B24: ACEROS DR SOC. ANONIMA | C24: 30711724997 | D24: Empresa | E24: Teodoro Plaza | F24: 3237 | G24: Ciudadela | H24: 1702 | I24: 259999 | J24: Metalúrgica | K24: Fabricación de productos elaborados de metal N.C.P. | S24: 4653-3183 | V24: http://acerosdr.com.ar/contacto.html
A25: C | B25: ACEROS INOXIDABLES ALVEAR S.R.L. | C25: 33715692649 | D25: Empresa | E25: Av. Marcelo T. de Alvear | F25: 2554 | G25: José Ingenieros | H25: 1703 | I25: 243100 | J25: Metalúrgica | K25: Cortes y plegados trabajos especiales en acero inoxidable para la industria gastronomica, farmaceutica, y de arquitectura | O25: Roberto | P25: 11 5569-2593 | S25: 4712-9130 | V25: No encontrado / No tiene
A26: C | B26: ACEROS INOXIDABLES CASEROS S.R.L. | C26: 30708161272 | D26: Empresa | E26: Av. Bartolomé Mitre | F26: 3244 | G26: Caseros | H26: 1678 | I26: 259999 | J26: Metalúrgica | K26: Fabricación de productos elaborados de metal N.C.P. | L26: B2B | N26: 26 | O26: Graciela Estente | P26: 11 6700-3265 | 11 4033-6448 | S26: 4734-1816 | T26: 4734-1613 | U26: 4750-5137 | 11 5322-8121 | V26: http://www.acerosinoxidablescaseros.com/ | W26: No | X26: No | Y26: Si
A27: C | B27: ACEROS MB S.A. | C27: 30584398694 | D27: Empresa | E27: General Villegas | F27: 4353 | G27: Caseros | H27: 1678 | I27: 241009 | J27: Metalúrgica | K27: Fabricación de industrias básicas de productos de hierro y acero N.C.P. (incluye la producción de hojalata) | N27: 62 | O27: Víctor M. Holub (Dir.) | P27: 11 4936-5726 | Q27: Juan Pablo Montan | R27: 11 3165-2541 | S27: 4759-1211 | 4936-5726 | T27: 4759-1092 | U27: 4750-9177 | V27: https://www.acerosmb.com.ar/ | W27: Si | X27: Si | Y27: Si
A28: F | B28: ACERPEL S.R.L. | C28: 30687238881 | D28: Empresa | E28: Ntra. Sra. de la Merced | F28: 3979 | G28: Caseros | H28: 1678 | I28: 282901 | J28: Metalúrgica | K28: Fabricación de maquinaria para la industria del papel y las artes gráficas | L28: B2B, BK | N28: 0 | S28: 4759-4802 | V28: No encontrado / No tiene | W28: No | X28: No | Y28: Si
A29: C | B29: ACHILLI VIVIANA Y ACHILLI DIEGO SOC. H. (HELADOS LOS AMORES) | C29: 33708320159 | D29: Empresa | E29: Martin Fierro | F29: 7853 | G29: Villa Bosch | H29: 1682 | I29: 105030 | J29: Alimenticia | K29: Elaboración industrial de helados | N29: 47 | O29: Diego Achilli (Concejal) | P29: 11 4992-6173 | S29: 11 5308-1563 | V29: https://los-amores.com.ar/ | W29: Si | X29: Si | Y29: Si
A30: C | B30: ACICA S.R.L. | C30: 30620246596 | D30: Empresa | E30: Av. Marcelo T. de Alvear | F30: 4492 | G30: Ciudadela | H30: 1702 | I30: 293099 | J30: Electrónica | K30: Fabricación de Aparatos y Accesorios Eléctricos N.C.P. | N30: 0 | S30: 11 4488-1599 | V30: No encontrado / No tiene | W30: Si | X30: Si | Y30: No
A31: C | B31: ACLAUJOR S.R.L. | C31: 30710864612 | D31: Empresa | E31: José Ignacio Rucci | F31: 65 | G31: Ciudadela | H31: 1702 | I31: 222109 | J31: Servicios | K31: Impresion excepto de diarios y revistas | N31: 0 | S31: 11 4657-2370 | V31: No encontrado / No tiene | W31: No | X31: No | Y31: Si
A32: F | B32: ACQUAIDEAS S.R.L. | C32: 30710015615 | D32: Empresa | E32: Agustín Cafferata | F32: 5196 | G32: Caseros | H32: 1678 | I32: 241009 | J32: Metalúrgica | K32: Fabricación en Industrias básicas de productos de Hierro y Acero N.C.P. | N32: 0 | S32: 4716-9334 | V32: No encontrado / No tiene | W32: No | X32: No | Y32: Si
A33: F | B33: ACQUAVAL S.R.L. | C33: 30637276499 | D33: Empresa | E33: Guaminí | F33: 5444 | G33: Caseros | H33: 1678 | I33: 289993 | J33: Metalúrgica | K33: Fabricación de productos metálicos de tornería y/o matricería | L33: B2B | N33: 0 | S33: 11 4734-6514 | V33: No encontrado / No tiene | W33: No | X33: No | Y33: Si
A34: C | B34: ACRILICOS AMENDOLA MARIANI S.R.L. | C34: 30647516366 | D34: Empresa | E34: Av. San Martín | F34: 1727 | G34: Caseros | H34: 1678 | I34: 222090 | J34: Plástica | K34: Fabricación de productos plásticos en formas básicas y artículos de plástico N.C.P., excepto muebles | L34: B2B | N34: 2 | O34: Carlos Améndola | P34: 11 4086-0033 | Q34: Oscar Jorge Mariani | R34: 15 4086-0033 | S34: 4512-7584 | T34: 4512-7583 | U34: 4512-7582 | V34: https://www.instagram.com/acrilicosamendola/?hl=es-la | W34: Si | X34: Si | Y34: Si
A35: F | B35: ACRILICOS DINAMICA S.R.L. | C35: 30586071099 | D35: Empresa | E35: Pueyrredón | F35: 3564 | G35: Ciudadela | H35: 1702 | I35: 390968 | J35: Metalúrgica | K35: Fabricación y armado letreros anuncios | N35: 0 | V35: No encontrado / No tiene | W35: No | X35: No | Y35: Si
A36: C | B36: ACRILICOS MAJO S.A. | C36: 30663738700 | D36: Empresa | E36: Av. Gaona | F36: 4019 | G36: Ciudadela | H36: 1702 | I36: 252090 | J36: Plástica | K36: Fabricación de productos plásticos en formas básicas y artículos de plástico N.C.P., excepto muebles | L36: B2B | N36: 0 | O36: José Bugner | P36: 4653-0722 | S36: 4653-0722 | V36: No encontrado / No tiene | W36: No | X36: No | Y36: Si
A37: C | B37: ACYTRA SAIC S.A. | C37: 30502185787 | D37: Empresa | E37: Av. Lope De Vega | F37: 2341 | G37: Villa Raffo | H37: 1674 | I37: 259309 | J37: Metalúrgica | K37: Fabricación de cerraduras, herrajes y artículos de ferretería N.C.P. | L37: B2C, B2B | M37: Cerraduras, candados | N37: 50 | O37: Pablo Oscar Gonzalez | P37: 11 5582-0350 | Q37: Matías Lacoppola | R37: 11 4043-9530 | S37: 11 4757-0729 | T37: 11 4757-3928 | U37: 11 5582-0360 | V37: https://acytra.com/ | W37: Si | X37: Si | Y37: Si
A38: C | B38: ADHE-MAX S.R.L. | C38: 30708208481 | D38: Empresa | E38: Federico Lacroze | F38: 3636 | G38: Ciudadela | H38: 1702 | I38: 202907 | J38: Química | K38: Fabricación de colas, adhesivos, aprestos y cementos excepto los odontológicos obtenidos de sustancias minerales y vegetales | N38: 3 | S38: 3750-7028 | T38: 4647-3413 | U38: 4647-0900 | V38: No encontrado / No tiene | W38: No | X38: No | Y38: Si
A39: C | B39: ADHEPLAST S.R.L. | C39: 30714362409 | D39: Empresa | E39: Av. Gral. Hornos | F39: 3186 | G39: Caseros | H39: 1678 | I39: 222090 | J39: Plástica | K39: Fabricación de productos plásticos en formas básicas y artículos de plástico N.C.P., excepto muebles | L39: B2B | N39: 1 | S39: 15 5108-4025 | T39: 11 5107-7456 | U39: 11 5434-2330 | V39: https://adheplastonline.com.ar/ | W39: No | X39: No | Y39: Si
A40: C | B40: ADITIVOS PLASTICOS S.R.L. | C40: 30708354011 | D40: Empresa | E40: Juan Larrea | F40: 3144 | G40: Caseros | H40: 1678 | I40: 202908 | J40: Química | K40: Fabricación de productos químicos N.C.P. (Incluye la producción de aceites esenciales, tintas excepto para imprenta, etc.) | N40: 4 | O40: Luis Riccitelli (Gerente) | P40: 15 5335-8743 | Q40: Víctor M. Holub | S40: 11 4751-2148 | T40: 11 4751-6480 | V40: https://aditivosplasticos.com/ | W40: Si | X40: Si | Y40: Si
A41: C | B41: ADREN S.A. | C41: 33710551699 | D41: Empresa | E41: Maldonado | F41: 283 | G41: Ciudadela | H41: 1702 | I41: 862110 | J41: Servicios | K41: Consultorio médico | N41: 3 | S41: 4657-1076 | V41: No encontrado / No tiene | W41: No | X41: No | Y41: Si
A42: C | B42: ADRIPLAST S.R.L. | C42: 30715841106 | D42: Empresa | E42: Diag. Bouchard | F42: 2731 | G42: Caseros | H42: 1678 | I42: 222010 | J42: Plástica | K42: Fabricación de envases plásticos | L42: B2B | O42: Juan Pablo Kaminski | P42: 15 4992-2848 | S42: 4716-0429 | V42: www.adriplast.com.ar | Y42: Si
A43: C | B43: AFONSO GARCIA GONZALO JAVIER (SOLUPLEX) | C43: 20262813720 | D43: Persona Física | E43: Santiago de Liniers | F43: 737 | G43: Ciudadela | H43: 1702 | I43: 702092 | J43: Plástica | K43: Servicios de asesoramiento, dirección y gestión empresarial realizados por integrantes de cuerpos de dirección en sociedades excepto las anónimas | L43: B2B | M43: Vasos starbucks, pochoclos | O43: Gonzalo Afonso (Director) | P43: 11 4181-4858 | Q43: Gerente Rodrigo Besteiro | S43: 11 2080-2771 | V43: http://www.soluplex.com.ar/#!/-bienvenidos/
A44: C | B44: AFTYKA SACHON INDUSTRIAS S.R.L. (AS INDUSTRIAS) | C44: 33708183909 | D44: Empresa | E44: Escultor Santiago Parodi | F44: 4773 | G44: Caseros | H44: 1678 | I44: 221909 | J44: Caucho | K44: Fabricación de productos de caucho N.C.P. | M44: Fuelles y soportes | N44: 18 | Q44: Jessica Saurina | R44: 11 6859-9904 | S44: 4101-0213 | T44: 4101-0067 | U44: 4101-0066 | V44: http://www.asindustrias.com.ar/ | W44: Si | X44: Si | Y44: Si
A45: C | B45: AG METALURGICA S.A. | C45: 30712300023 | D45: Empresa | E45: Fernández de Oliveira | F45: 4626 | G45: Caseros | H45: 1678 | I45: 259999 | J45: Metalmecánica | K45: Fabricación de productos elaborados de metal N.C.P. | L45: B2B | N45: 20 | O45: Eduardo Ares (Pte.) | P45: 11 6958-7565 | Q45: Ariel Ares | R45: 11 6958-2538 | S45: 11 7532-5048 | T45: 11 7532-5048 Int. 4 | U45: 11) 7532-5048 Int. 2 | V45: https://agmetalurgica.com.ar/ | W45: No | X45: No | Y45: Si
A46: C | B46: AGASI GUILLERMO | C46: 23229314629 | D46: Persona Física | E46: Guaminí | F46: 5050 | G46: Caseros | H46: 1678 | I46: 259993 | J46: Metalúrgica | K46: Fabricación de productos metálicos de tornería y/o matricería | L46: B2B | S46: 15 4195-8404 | V46: No encontrado / No tiene
A47: C | B47: AGENCAISSA S.A. | C47: 30548270622 | D47: Empresa | E47: Tte. Gral. Pablo Ricchieri | F47: 3542 | G47: Ciudadela | H47: 1702 | I47: 170990 | J47: Papel | K47: Fabricación de artículos de papel y cartón N.C.P. (no incluye el papel de lija: 239900) | L47: B2C, B2B | M47: Agenda, anotadores, papel, papel guia. | N47: 13 | O47: Miriam Di Diego | S47: 11 6740-4202 | V47: https://caissa.com.ar/ | W47: Si | X47: Si | Y47: Si
A48: F | B48: AGUA MORGADE S.A. | C48: 30716890275 | D48: Empresa | E48: Santa Rita | F48: 8310 | G48: Loma Hermosa | H48: 1657 | I48: 110412 | J48: Bebidas | K48: Elaboración de sodas, aguas minerales y bebidas analcohólicas | S48: 4769-9692 | T48: 4769-0824 | V48: http://www.aguamineralmorgade.com.ar/ | Y48: Si
A49: F | B49: AGUIRRE ROGELIO EDUARDO Y GONZALEZ EDUARDO S.H. | C49: 30701153878 | D49: Empresa | E49: Av. La Plata | F49: 3471 | G49: Santos Lugares | H49: 1676 | I49: 642020 | J49: Servicios | K49: Reparación y pintura de carrocerías; colocación y reparación de guardabarros y protecciones exteriores | N49: 0 | S49: 4712-7321 | T49: 4712-7320 | U49: 4712-7319 | V49: No encontrado / No tiene | W49: No | X49: No | Y49: Si
A50: F | B50: AGUIRRE ROGELIO EDUARDO Y GONZALEZ EDUARDO S.H. | C50: 33707612229 | D50: Persona Física | E50: Pablo Poggio | F50: 793 | G50: Villa Bosch | H50: 1682 | I50: 154120 | J50: Alimenticia | K50: Elaboración Industrial de productos de Panadería, excluido Galletitas y Bizcochos | N50: 2 | S50: 4844-4278 | V50: No encontrado / No tiene | W50: No | X50: No | Y50: Si
A51: F | B51: AGUSTI PELLICANI S.H. | C51: 30685304666 | D51: Empresa | E51: Blvd. San Martín | F51: 3086 | G51: Ciudad Jardín Lomas del Palomar | H51: 1684 | I51: 522999 | J51: Alimenticia | K51: Matanza de Ganado. Mataderos | M51: Local? | N51: 1 | S51: 11 4751-2923 | T51: 11 4758-0014 | V51: No encontrado / No tiene | W51: No | X51: No | Y51: Si
A52: C | B52: AIMAN S.A. | C52: 33646972979 | D52: Empresa | E52: Av. Diaz Velez | F52: 1066 | G52: Ciudadela | H52: 1702 | I52: 139202 | J52: Textil | K52: Fabricación de ropa de cama y mantelería | L52: B2C, B2B | M52: almohadas, frazadas, sabanas, manteles, toallas, cortinas | N52: 47 | O52: Ruben Roussilian | S52: 4653-1104 | 4653-1178 | T52: 4653-0702 | U52: 4488-1849 | V52: www.aiman-sa.com/ | W52: Si | X52: No | Y52: Si
A53: C | B53: AITEC INGENIERIA S.R.L. | C53: 30595980425 | D53: Empresa | E53: Río Atuel | F53: 9744 | G53: Loma Hermosa | H53: 1657 | I53: 266090 | J53: Metalúrgica | K53: Fabricación de equipo médico y quirúrgico y de aparatos ortopédicos N.C.P. | L53: B2B | M53: Trabajos a pedido en acero inoxidable | N53: 9 | S53: 11 3969-3851 | T53: 15 5642-8935 | V53: http://aitec-ingenieria.com.ar/ | W53: Si | X53: Si | Y53: Si
A54: F | B54: AITUE DESARROLLOS URBANOS S.A. | C54: 30711925100 | D54: Empresa | E54: Av. Maipú | F54: 3985 | G54: Ciudadela | H54: 1702 | I54: 410021 | J54: Construcción | K54: Construcción, reforma y reparación de edificios no residenciales (incluye construcción, reforma y reparación de restaurantes, bares, campamentos, bancos, oficinas, galerías comerciales, estaciones de servicio, edificios para tráfico y comunicaciones, garajes, edificios industriales y depósitos, escuelas, etc.) | L54: B2B | N54: 2 | S54: 3979-8214 | T54: 1126862270 | V54: https://www.instagram.com/aitue.desarrollos/ | W54: No | X54: No | Y54: Si
A55: C | B55: AL GREMIO HERRAJES S.R.L. | C55: 33709956669 | D55: Empresa | E55: Av. Marcelo T. de Alvear | F55: 2288 | G55: José Ingenieros | H55: 1702 | I55: 466330 | J55: Metalúrgica | K55: Venta al por mayor de artículos de ferretería y materiales eléctricos | L55: B2B | M55: Distribuidora de Herrajes & Bazar Deco | N55: 0 | S55: 11 5257-7103 | T55: 11 5257-7105 | V55: https://www.instagram.com/al.gremioherrajes/ | W55: No | X55: No | Y55: Si
A56: C | B56: AL FUNDICION S.R.L. | C56: 30710612214 | D56: Empresa | E56: Agustín Cafferata | F56: 5830 | G56: Caseros | H56: 1678 | I56: 243200 | J56: Metalúrgica | K56: Fundición de metales no ferrosos | L56: B2B | M56: Funciones | N56: 3 | O56: Germán Volpini | S56: 4758-4828 | V56: No encontrado / No tiene | W56: No | X56: No | Y56: Si
A57: C | B57: ALAMBRES INDUSTRIALES TREFILADOS S.R.L. (ACEROS VILLA BOSCH S.A.) | C57: 30647279909 | D57: Empresa | E57: Manuela Pedraza | F57: 973 | G57: Villa Bosch | H57: 1682 | I57: 241009 | J57: Metalúrgica | K57: Fabricación de productos elaborados de metal N.C.P. | L57: B2B | M57: Alambres | N57: 59 | O57: Gabriel A. Czumadewski | P57: 11 3691-8935 | Q57: Marcelo G. Lazzaro | R57: 11 3681-8937 | S57: Planta: 4769-8353 (Fabian) | T57: Oficina: Mónica Berdiuk 4842-6700/5800 Andres (hijo) | U57: 11 6726-0062 (Maria Angela Fusetti) | V57: http://www.acerosbosch.com.ar/ | W57: Si | X57: Si | Y57: Si
A58: C | B58: ALBALONGA S.A. | C58: 30595286189 | D58: Empresa | E58: 1 de Mayo | F58: 1684 | G58: Pablo Podestá | H58: 1657 | I58: 131300 | J58: Textil | K58: Acabado de productos textiles | N58: 48 | O58: Karina Aragón| Roberta Donati, Tel: (11 4769-0109 |15 4993-9693) | P58: 11 4993-9693 | Q58: Bartolome Donati | R58: 11 5423-5802 | S58: 4769-0109 | T58: 4769-4750 | U58: 4769-4751 | V58: https://www.albalonga.com.ar/ | W58: Si | X58: No | Y58: Si
A59: C | B59: ALCIDES L TESSA S.R.L. | C59: 30663767700 | D59: Empresa | E59: Cnel. Pringles | F59: 3711 | G59: Caseros | H59: 1678 | I59: 329090 | J59: Metalúrgica | K59: Industrias manufactureras N.C.P. (Incluye fabricación de paraguas, termos, pelucas, etc.) | N59: 31 | S59: 11 4716-0909 | T59: 11 4750-1822 | U59: 11 4750-7142 | V59: https://www.alcidestessa.com.ar/ | W59: Si | X59: Si | Y59: Si
A60: C | B60: ALDANA RAMON ALFREDO Y MAMMANA MAXIMILIANO ANDRES S.H. | C60: 33712087949 | D60: Empresa | E60: Catrilo | F60: 5195 | G60: Caseros | H60: 1678 | I60: 107110 | J60: Alimenticia | K60: Elaboración de galletitas y bizcochos | M60: Merengue | N60: 4 | O60: Carlos De Merlier | S60: 5435-8975 | V60: No encontrado / No tiene | W60: Si | X60: Si | Y60: Si
A61: C | B61: ALEJANDRO BARBIERI Y SERGIO BARBIERI SOC. DE HECHO | C61: 30712203338 | D61: Persona Física | E61: Olavarría | F61: 4650 | G61: Caseros | H61: 1678 | I61: 259200 | J61: Metalúrgica | K61: Tratamiento y revestimiento de metales y trabajos de metales en general | L61: B2B | N61: 0 | S61: 4600-3807 | T61: 4654-7316 | V61: No encontrado / No tiene | W61: No | X61: No | Y61: Si
A62: F | B62: ALEJANDRO GAMINO ALBERTO GAMINO (CICLO?) | C62: 30708330392 | D62: Persona Física | E62: Agustín Cafferata | F62: 5188 | G62: Caseros | H62: 1678 | I62: 259100 | J62: Metalúrgica | K62: Forjado, prensado, estampado y laminado de metales; pulvimetalurgia | L62: B2B | N62: 0 | S62: 4782-0518 | V62: No encontrado / No tiene | W62: No | X62: No | Y62: Si
A63: F | B63: ALFA DE BLAZER OSVALDO Y PERAZZELLI PEDRO | C63: 30663744220 | D63: Persona Física | E63: Fray Justo Sta. María de Oro | F63: 4642 | G63: Caseros | H63: 1678 | I63: 259301 | J63: Metalúrgica | K63: Fabricación de herramientas manuales y sus accesorios | N63: 0 | S63: 11 4750-0246 | V63: No encontrado / No tiene | W63: No | X63: No | Y63: Si
A64: C | B64: ALFONSO SABBATINI E HIJO S.R.L. | C64: 30709636991 | D64: Empresa | E64: Montevideo | F64: 1658 | G64: Ciudadela | H64: 1702 | I64: 281201 | J64: Metalúrgica | K64: Fabricación de bombas. Fabricación de compresores, grifos y válvulas | N64: 18 | O64: Alejandro Sabbatini | Eduardo Sabbatini | P64: 11 3809-4099 | 11 3273-9618 | Q64: Agustin Romero | S64: 11 3480-8093 | T64: 11 4653-2728 | V64: https://www.sabbatini.com.ar/ | W64: Si | X64: Si | Y64: Si
A65: C | B65: ALFONSO SABBATINI E HIJO S.R.L. | C65: 30709636991 | D65: Empresa | E65: Montevideo | F65: 1658 | G65: Ciudadela | H65: 1702 | I65: 281201 | J65: Metalúrgica | K65: Fabricación de bombas | M65: Bombas | N65: 18 | O65: Eduardo Sabbatini | P65: 11 3273-9618 | Q65: Agustin Romero | R65: 11 3480-8093 | S65: 4600-8514 | T65: 4657-2927 | U65: 4653-2728 | V65: https://www.sabbatini.com.ar/
A66: F | B66: ALGODONERA VILLAFER S.R.L. | C66: 30656718761 | D66: Empresa | E66: Angel Pini | F66: 5445 | G66: Caseros | H66: 1678 | I66: 321028 | J66: Textil | K66: Preparación de Fibras de Algodón | N66: 0 | S66: 4734-4049 | V66: No encontrado / No tiene | W66: No | X66: No | Y66: Si
A67: F | B67: ALIMENTARIA CARHUE S.R.L. | C67: 30683370505 | D67: Empresa | E67: Carhué | F67: 5476 | G67: Caseros | H67: 1678 | I67: 153131 | J67: Alimenticia | K67: Elaboración de alimentos a base de cereales | M67: Alfajores y galletitas en paquetes pequeños | N67: 2 | S67: 15 4061-9780 | T67: 4469-0442 | V67: No encontrado / No tiene | W67: No | X67: No | Y67: Si
A68: F | B68: ALIMENTOS AGRELE S.R.L. (CRISPPINO) | C68: 30714502367 | D68: Empresa | E68: Dardo Rocha | F68: 1175 | G68: Santos Lugares | H68: 1676 | I68: 463199 | J68: Alimenticia | K68: Venta por mayor de productos alimenticios N.C.P. | L68: B2B | M68: Alimentos para celiacos | O68: Juan Greco | Oliver Lehmann | P68: 1155670353 | V68: https://www.instagram.com/crisppino/?hl=es
A69: C | B69: ALIMENTOS BACIGALUPO S.A. | C69: 30708664762 | D69: Empresa | E69: 9 de Julio | F69: 2189 | G69: Ciudadela | H69: 1702 | I69: 107991 | J69: Alimenticia | K69: Elaboración de extractos, jarabes y concentrados | S69: 4115-6428/6480 | T69: 41397834/35 | U69: 4647-1920/26 | V69: http://bacigalupo.com.ar/
A70: C | B70: ALIMENTOS ESPECIFICOS S.A. (KAPAC) | C70: 30661450602 | D70: Empresa | E70: Olavarría | F70: 3435/27 | G70: Caseros | H70: 1678 | I70: 107999 | J70: Alimenticia | K70: Elaboración de productos alimenticios N.C.P. (Incluye la elaboración de polvos para preparar postres y gelatinas, levadura, productos para copetín, sopas, sal de mesa, mayonesa, mo | N70: 25 | O70: Camila | P70: 11 3051-2812 | Q70: Nicolas Aldo Ripari | S70: 4300-2993 | T70: 4716-6699 | V70: https://kapac.com.ar/ | W70: Si | X70: Si | Y70: Si
A71: C | B71: ALIMENTOS NOLY S. A. (DOÑA NOLY) | C71: 30583370028 | D71: Empresa | E71: Av. Marcelo T. de Alvear | F71: 4497 | G71: Caseros | H71: 1678 | I71: 107410 | J71: Alimenticia | K71: Elaboración industrial de productos de panadería, excepto galletitas y bizcochos (Incluye la elaboración de productos de panadería frescos, congelados y secos) | N71: 227 | O71: Nicolas Arrojo | P71: 11 5761-4151 | Q71: Pablo Valentino | R71: 15 3090-6367 | S71: 11 6756-7703 | T71: 11 4144-9454 (Claudia Mariani) | U71: 11 3071-4845 | V71: www.noly.com.ar | W71: Si | X71: Si | Y71: Si
A72: C | B72: ALIMENTOS SILVA S.A. | C72: 30710162669 | D72: Empresa | E72: San Lorenzo | F72: 1318 | G72: Villa Bosch | H72: 1682 | I72: 107992 | J72: Alimenticia | K72: Elaboración de vinagres | L72: B2B | M72: Vinagre | N72: 11 | O72: Daniel D'Ippolito | P72: 6560-1879 | Q72: Yanina Centurión | R72: 4623-3315 interno 209 | S72: 11 4844-3393 | V72: https://www.instagram.com/silva_sapori/?hl=es | W72: No | X72: No | Y72: Si
A73: C | B73: ALL CLEAN GROUP S.R.L. | C73: 30711417776 | D73: Empresa | E73: Croacia | F73: 3061 | G73: Ciudadela | H73: 1702 | I73: 170990 | J73: Papel | K73: Fabricación de artículos de papel y cartón N.C.P. | M73: Productos químicos para limpieza | distribuidora minorista y mayorista | N73: 22 | S73: 4488-6800 | 5009-6570 (particular) | T73: 4657-4819 | 11 5009-5709 | U73: 4657-5679 | V73: https://www.quimicaallclean.com.ar/ | https://allcleanmayorista.com.ar/ | W73: Si | X73: Si | Y73: Si
A74: F | B74: ALLOCATI SANTIAGO MARIO | C74: 20283057608 | D74: Persona Física | E74: Av. Bernabé Márquez | F74: 2521 Dpto:4 M:78 | G74: Pablo Podestá | H74: 1657 | I74: 614010 | J74: Servicios | K74: Servicios de proveedores de acceso a internet | S74: 6091-7878 | V74: No encontrado / No tiene
A75: C | B75: ALMAR TABLE TENNIS S.R.L. | C75: 30711181551 | D75: Empresa | E75: Sarmiento | F75: 3863 | G75: Caseros | H75: 1678 | I75: 323001 | J75: Metalúrgica | K75: Fabricación de artículos de deporte (Incluye equipos de deporte para gimnasia y campos de juegos, equipos de pesca y camping, etc., excepto indumentaria deportiva: 141040) | M75: Mesas de Ping Pong | N75: 4 | O75: Pablo Gómez (Socio gte.) | P75: 11 6011-3125 | S75: 11 3406-9970 | T75: 11 3154-4760 | U75: 11 3406-9970 | V75: https://almartenisdemesa.com.ar/ | W75: No | X75: No | Y75: Si
A76: F | B76: ALMIRON HNOS | C76: 30663765724 | D76: Empresa | E76: Tucumán | F76: 1848 | G76: Loma Hermosa | H76: 1657 | I76: 361010 | J76: Madera | K76: Fabricación de muebles y partes de muebles, principalmente de madera | L76: B2C, B2B | N76: 2 | S76: 4841-1364 | V76: No encontrado / No tiene | W76: No | X76: No | Y76: Si
A77: F | B77: ALONSO HNOS | C77: 33504483539 | D77: Empresa | E77: Gazeta de Buenos Aires | F77: 3661 | G77: Ciudadela | H77: 1702 | I77: 369999 | J77: Manufactura | K77: Industrias manufactureras N.C.P. (incluye fabricación de cochecitos de bebé, termos, velas, pelucas, etc.) | N77: 0 | S77: 4653-6766 | T77: 4657-9893 | U77: 4653-7432 | V77: No encontrado / No tiene | W77: No | X77: No | Y77: Si
A78: C | B78: ALONSO RUBIÑOS DIEGO (MATRICERIA ALONSO) | C78: 20253587718 | D78: Persona Física | E78: Pampa | F78: 3876 Piso:PB | G78: Ciudadela | H78: 1702 | I78: 259993 | J78: Metalmecánica | K78: Fabricación de productos metálicos de tornería y/o matricería | L78: B2B | S78: 15 6641-8830 | V78: No encontrado / No tiene
A79: C | B79: ALPHA S.R.L. | C79: 30503248405 | D79: Empresa | E79: Caxaraville | F79: 3761 | G79: Ciudadela | H79: 1702 | I79: 281201 | J79: Metalúrgica | K79: Fabricación de bombas | N79: 2 | S79: 4488-8663 | T79: 4653-2545 | V79: No encontrado / No tiene | W79: No | X79: No | Y79: Si
A80: C | B80: ALPRIN S.R.L. | C80: 30708138246 | D80: Empresa | E80: Juan de Garay | F80: 4848 | G80: Caseros | H80: 1678 | I80: 170202 | J80: Papel | K80: Fabricación de cartón ondulado y envases de cartón | M80: Producción de estuches y soluciones integrales en packaging | N80: 20 | O80: Pablo Gebtsberger | P80: 15 5333-4401 | S80: 11 5706-1772 | T80: 4716-2018 | U80: 4734-6494 | V80: https://alprin.com.ar/ | W80: Si | X80: Si | Y80: Si
A81: F | B81: ALTA ROMA S.A. | C81: 33711684099 | D81: Empresa | E81: Río Jáchal | F81: 957 | G81: Loma Hermosa | H81: 1657 | I81: 152011 | J81: Calzado | K81: Fabricación de calzado de cuero, excepto calzado deportivo y ortopédico | N81: 8 | S81: 4769-0795 | V81: No encontrado / No tiene | W81: No | X81: No | Y81: Si
A82: F | B82: ALTAMIX S.A. | C82: 30708397349 | D82: Empresa | E82: San Agustin | F82: 795 | G82: Ciudadela | H82: 1702 | I82: 343000 | J82: Automotor | K82: Fabricación de partes, piezas y accesorios para vehículos automotores y sus motores | N82: 0 | S82: 4653-9230 | V82: No encontrado / No tiene | W82: Si | X82: Si | Y82: Si
A83: C | B83: ALTRON DE SERGIO ANTONIO SALIGARI Y EDUARDO ALBERTO TOLOSA SOC. H. | C83: 30568774783 | D83: Empresa | E83: Marco Polo | F83: 5579 | G83: Villa Bosch | H83: 1682 | I83: 241009 | J83: Metalúrgica | K83: Tratamiento y revestimiento de metales y trabajos de metales en general (Incluye la producción de hojalata) | N83: 3 | S83: 4751-5444 | T83: 5435-6972 | V83: No encontrado / No tiene | W83: No | X83: No | Y83: Si
A84: C | B84: ALUMETAL S.R.L. | C84: 30701152715 | D84: Empresa | E84: Fray Cayetano Rodriguez | F84: 2534 | G84: Ciudadela | H84: 1702 | I84: 251101 | J84: Metalúrgica | K84: Fabricación de carpintería metálica | L84: B2B | M84: Metalúrgica especializada en carpintería de aluminio y PVC | N84: 15 | O84: María Noel de Armas | P84: 11 4712-9632 | S84: 11 4712-9632 | T84: 11 3705-6638 | V84: https://alumetal.com.ar/ | W84: Si | X84: Si | Y84: Si
A85: C | B85: ALUMINIO REAL S.A. | C85: 30710800231 | D85: Empresa | E85: Betharram | F85: 967 | G85: Villa Bosch | H85: 1682 | I85: 259302 | J85: Metalúrgica | K85: Fabricación de artículos de cuchillería y utensillos de mesa y de cocina | L85: B2B, B2C | M85: Ollas, menajes | N85: 18 | O85: Sergio Fedele | P85: 11 6576-6030 | S85: 4842-2380 | T85: 11 4842-5585 | V85: https://aluminioreal.com.ar/ | W85: Si | X85: Si | Y85: Si
A86: C | B86: ALUOEST S.A.C.I.F.I.A. (ALUOEST S.A.) | C86: 30556285965 | D86: Empresa | E86: Av. Gaona | F86: 3646 | G86: Ciudadela | H86: 1702 | I86: 251101 | J86: Metalúrgica | K86: Fabricación de carpintería metálica. Venta al por mayor de metales y minerales metalíferos | L86: B2B | M86: Línea de productos basados en el aluminio desde perfiles y laminados, coberturas telescópicas para piscinas, sistema de iluminación tubular y las ventanas para techo italianas. | N86: 28 | O86: María Fernanda Caudarella | Carla (Secretaria) | P86: 11 4945-9507 | Q86: María Fernanda | R86: 11 4028-0426 | S86: 11 4608-5000 | T86: 11 4088-1785 | V86: https://www.aluoest.com.ar/ | W86: Si | X86: Si | Y86: Si
A87: C | B87: ALVAREZ LUIS ALBERTO (FABRICA DE MUEBLES FRH) | C87: 20148682195 | D87: Persona Física | E87: 9 de Julio | F87: 1540 | G87: Ciudadela | H87: 1702 | I87: 310010 | J87: Madera | K87: Fabricación de muebles | L87: B2C | M87: Muebles | S87: 4488-5013 | T87: 4488-4743 | V87: No encontrado / No tiene | Y87: Si
A88: F | B88: ALVES PEREYRA J M MIRANDA J A BEZERRA Y CIA | C88: 33601022309 | D88: Empresa | E88: Chubut | F88: 4630 | G88: Ciudadela | H88: 1702 | I88: 269301 | J88: Construcción | K88: Fabricación de Ladrillos | L88: B2B | N88: 0 | S88: 4712-6931 | V88: No encontrado / No tiene | W88: No | X88: No | Y88: Si
A89: C | B89: ALVES ROLO GERARDO ENRIQUE Y GIUSTINA RUBEN ANIBAL | C89: 30625688651 | D89: Empresa | E89: Besares | F89: 2650 | G89: José Ingenieros | H89: 1702 | I89: 275099 | J89: Metalmecánica | K89: Fabricación de aparatos de uso doméstico N.C.P. (Incluye enceradoras, pulidoras, batidoras, licuadoras y similares) | M89: caños flexibles, tubos | N89: 0 | S89: 4712-6931 | T89: 11 4757-4760 | U89: 11 4757-1085 | V89: www.flexitub.com.ar | W89: No | X89: No | Y89: Si
A90: F | B90: ALYGU S.R.L. | C90: 30685324861 | D90: Empresa | E90: Blvd. San Martín | F90: 3089 | G90: Ciudad Jardín Lomas del Palomar | H90: 1684 | I90: 452100 | J90: Construcción | K90: Construcción, Reforma y Reparación de Edificios Residenciales | L90: B2B | N90: 0 | S90: 4734-1198 | T90: 4734-1995 | U90: 4750-9999 | V90: No encontrado / No tiene | W90: No | X90: No | Y90: Si
A91: F | B91: AMAGLA CYS S.R.L. | C91: 30711346380 | D91: Empresa | E91: Asamblea | F91: 4266 | G91: Santos Lugares | H91: 1676 | I91: 410021 | J91: Construcción | K91: Construcción, reforma y reparación de edificios no residenciales | L91: B2B | N91: 0 | S91: 4716-0770 | T91: 4716-4510 | V91: No encontrado / No tiene | W91: No | X91: No | Y91: Si
A92: C | B92: AMALGRAF S.R.L. | C92: 30654784082 | D92: Empresa | E92: Escultor Santiago Parodi | F92: 4293 | G92: Caseros | H92: 1678 | I92: 181109 | J92: Gráfica | K92: Impresión N.C.P., excepto de diarios y revistas | M92: Packaging | N92: 14 | O92: Adriana Desteffanis | P92: 11 5183-8586 | Q92: Julian Zuccaro | R92: 1121581117 | S92: 11 4716-0770 | T92: 11 4716 4510 | V92: https://amalgraf.com.ar/ | W92: No | X92: No | Y92: Si
A93: F | B93: AMAS DE MONTERO S.R.L. | C93: 30715160486 | D93: Empresa | E93: Seneca | F93: 2124 | G93: Santos Lugares | H93: 1676 | I93: 429090 | J93: Construcción | K93: Construcción de obras de ingeniería civil N.C.P. | L93: B2B | N93: 0 | O93: Alfredo Montero | P93: 15 6039-7368 | S93: 4712-6945 | V93: No encontrado / No tiene | W93: No | X93: No | Y93: Si
A94: C | B94: AMENDOLA ROSA KARINA (Rosa Karina Amendola LK maderas (Ex IPLO)) | C94: 27925199759 | D94: Persona Física | E94: Miguel de Azcuénaga | F94: 4638 | G94: Caseros | H94: 1678 | I94: 141130 | J94: Madera | K94: Confección de prendas de vestir para bebés y niños | N94: 2 | S94: 11 5763-5957 | V94: https://es-la.facebook.com/iplo.babykids/ | Y94: Si
A95: C | B95: AMENTUEL S.A. | C95: 30691156377 | D95: Empresa | E95: Asunción | F95: 4743 | G95: Ciudadela | H95: 1702 | I95: 107309 | J95: Alimenticia | K95: Elaboración de productos de confitería N.C.P. (Incluye alfajores, caramelos, frutas confitadas, pastillas, gomas de mascar, etc.) | M95: Productos para decorar tortas | N95: 30 | O95: Daniel Dordoni | P95: 1167515385 | Q95: Daniel Dordoni | R95: 11 6751-5454 | S95: 11 4653-5082 | V95: https://www.amentuel.com.ar/ | W95: Si | X95: Si | Y95: Si
A96: C | B96: AMOBLAMIENTOS AJUVA S.R.L. | C96: 30715720244 | D96: Empresa | E96: Martín Peschel | F96: 1465 | G96: Pablo Podestá | H96: 1657 | I96: 310010 | J96: Madera | K96: Fabricación de muebles y partes de muebles, principalmente de madera | L96: B2C | M96: Muebles de baño, maral, mates y decoración | N96: 3 | O96: Fernando | S96: 4848-9512 | T96: 4757-6062 | V96: https://www.instagram.com/ajuva.olgui/ | W96: No | X96: No | Y96: Si
A97: C | B97: AMOBLAMIENTOS DAS SOLUCIONES S.R.L. | C97: 30708976101 | D97: Empresa | E97: Francisco Madero | F97: 747 | G97: Ciudadela | H97: 1702 | I97: 310010 | J97: Madera | K97: Fabricación de muebles y partes de muebles, principalmente de madera | L97: B2C, B2B | M97: Amoblamientos para farmacias, perfumerías, laboratorios y ópticas | N97: 11 | O97: Patricia A. Mouriño | S97: 11 6848-8704 | T97: 11 7395-6400 | V97: https://dassoluciones.com.ar/ | W97: No | X97: No | Y97: Si
A98: C | B98: AMOBLAMIENTOS RIZZUTO S.R.L. | C98: 30685268767 | D98: Empresa | E98: Manuel Bermúdez | F98: 4426 | G98: Caseros | H98: 1678 | I98: 310010 | J98: Madera | K98: Fabricación de muebles y partes de muebles, principalmente de madera | L98: B2C, B2B | N98: 6 | S98: 4750-4739 | V98: No encontrado / No tiene | W98: No | X98: No | Y98: Si
A99: F | B99: AMS ACEROS | C99: 33715900829 | D99: Empresa | E99: Av. Bartolomé Mitre | F99: 4135 | G99: Caseros | H99: 1678 | I99: 259999 | J99: Metalúrgica | K99: Fabricación de productos elaborados de metal N.C.P. | S99: 5278-4888 | T99: 11 6106-4888 | U99: 5278-4888 | 4759-4888 | V99: https://amsaceros.com/
A100: F | B100: AN RO DE LONGO Y DONATI R S.H. | C100: 30649713045 | D100: Persona Física | E100: Esteban Merlo | F100: 5157 | G100: Caseros | H100: 1678 | I100: 324019 | J100: Calzado | K100: Fabricación de Calzado de Cuero | N100: 0 | S100: 11 4750-2636 | V100: No encontrado / No tiene | W100: No | X100: No | Y100: Si
...

Sheet Mails_Normalizados
A1: EMPRESA | B1: CUIT | C1: RUBRO | D1: EMAIL | E1: TIPO | F1: ESTADO
A2: Razón Social AFIP | D2: leomellimurano@gmail.com | E2: Principal | F2: funcional
A3: Razón Social AFIP | D3: patricianoemireynoso@gmail.com | E3: Principal | F3: funcional
A4: 1989 ESTUDIO A S.R.L. | ALEJANDRO Y MIGUEL ANGEL RIZZI S.H. | B4: =IF(A4="", "", IF(IFERROR(VLOOKUP(A4, 'Base 3F'!$B:$C, 2, FALSE),"")="", "SIN CUIT", VLOOKUP(A4, 'Base 3F'!$B:$C, 2, FALSE))) -> 30709328995 | 30710682816 | C4: =IF(A4="", "", IF(IFERROR(VLOOKUP(A4, 'Base 3F'!$B:$J, 9, FALSE),"")="", "SIN RUBRO", VLOOKUP(A4, 'Base 3F'!$B:$J, 9, FALSE))) -> Papel | D4: angelina@estudioapop.com.ar | E4: Principal | F4: funcional
A5: A D S.A. | B5: =IF(A5="", "", IF(IFERROR(VLOOKUP(A5, 'Base 3F'!$B:$C, 2, FALSE),"")="", "SIN CUIT", VLOOKUP(A5, 'Base 3F'!$B:$C, 2, FALSE))) -> 30710393725 | C5: =IF(A5="", "", IF(IFERROR(VLOOKUP(A5, 'Base 3F'!$B:$J, 9, FALSE),"")="", "SIN RUBRO", VLOOKUP(A5, 'Base 3F'!$B:$J, 9, FALSE))) -> Metalúrgica | D5: lgreco@amasd.com.ar | E5: Principal | F5: funcional
A6: ABELARDO ESTEBAN (VALVULAS ESTEBAN) | B6: =IF(A6="", "", IF(IFERROR(VLOOKUP(A6, 'Base 3F'!$B:$C, 2, FALSE),"")="", "SIN CUIT", VLOOKUP(A6, 'Base 3F'!$B:$C, 2, FALSE))) -> 20105339330 | C6: =IF(A6="", "", IF(IFERROR(VLOOKUP(A6, 'Base 3F'!$B:$J, 9, FALSE),"")="", "SIN RUBRO", VLOOKUP(A6, 'Base 3F'!$B:$J, 9, FALSE))) -> Metalúrgica | D6: liliappardo@yahoo.com.ar | E6: Principal | F6: funcional
A7: ACEROS COFER S.A. | B7: =IF(A7="", "", IF(IFERROR(VLOOKUP(A7, 'Base 3F'!$B:$C, 2, FALSE),"")="", "SIN CUIT", VLOOKUP(A7, 'Base 3F'!$B:$C, 2, FALSE))) -> 30707576444 | C7: =IF(A7="", "", IF(IFERROR(VLOOKUP(A7, 'Base 3F'!$B:$J, 9, FALSE),"")="", "SIN RUBRO", VLOOKUP(A7, 'Base 3F'!$B:$J, 9, FALSE))) -> Metalúrgica | D7: juancluna@aceroscofer.com.ar | E7: Principal | F7: funcional
A8: ACEROS INOXIDABLES ALVEAR S.R.L. | B8: 33715692649 | C8: =IF(A8="", "", IF(IFERROR(VLOOKUP(A8, 'Base 3F'!$B:$J, 9, FALSE),"")="", "SIN RUBRO", VLOOKUP(A8, 'Base 3F'!$B:$J, 9, FALSE))) -> Metalúrgica | D8: info@acerosalvear.com | E8: Principal | F8: rebotado_desconocido
A9: ACEROS INOXIDABLES CASEROS S.R.L. | B9: =IF(A9="", "", IF(IFERROR(VLOOKUP(A9, 'Base 3F'!$B:$C, 2, FALSE),"")="", "SIN CUIT", VLOOKUP(A9, 'Base 3F'!$B:$C, 2, FALSE))) -> 30708161272 | C9: =IF(A9="", "", IF(IFERROR(VLOOKUP(A9, 'Base 3F'!$B:$J, 9, FALSE),"")="", "SIN RUBRO", VLOOKUP(A9, 'Base 3F'!$B:$J, 9, FALSE))) -> Metalúrgica | D9: graciela@inoxicaseros.com.ar | E9: Principal | F9: funcional
A10: ACEROS MB S.A. | B10: =IF(A10="", "", IF(IFERROR(VLOOKUP(A10, 'Base 3F'!$B:$C, 2, FALSE),"")="", "SIN CUIT", VLOOKUP(A10, 'Base 3F'!$B:$C, 2, FALSE))) -> 30584398694 | C10: =IF(A10="", "", IF(IFERROR(VLOOKUP(A10, 'Base 3F'!$B:$J, 9, FALSE),"")="", "SIN RUBRO", VLOOKUP(A10, 'Base 3F'!$B:$J, 9, FALSE))) -> Metalúrgica | D10: vholub@acerosmb.com.ar | E10: Principal | F10: funcional
A11: ACHILLI VIVIANA Y ACHILLI DIEGO SOC. H. (HELADOS LOS AMORES) | B11: =IF(A11="", "", IF(IFERROR(VLOOKUP(A11, 'Base 3F'!$B:$C, 2, FALSE),"")="", "SIN CUIT", VLOOKUP(A11, 'Base 3F'!$B:$C, 2, FALSE))) -> 33708320159 | C11: =IF(A11="", "", IF(IFERROR(VLOOKUP(A11, 'Base 3F'!$B:$J, 9, FALSE),"")="", "SIN RUBRO", VLOOKUP(A11, 'Base 3F'!$B:$J, 9, FALSE))) -> Alimenticia | D11: dachilli@los-amores.com.ar | E11: Principal | F11: funcional
A12: ADITIVOS PLASTICOS S.R.L. | B12: =IF(A12="", "", IF(IFERROR(VLOOKUP(A12, 'Base 3F'!$B:$C, 2, FALSE),"")="", "SIN CUIT", VLOOKUP(A12, 'Base 3F'!$B:$C, 2, FALSE))) -> 30708354011 | C12: =IF(A12="", "", IF(IFERROR(VLOOKUP(A12, 'Base 3F'!$B:$J, 9, FALSE),"")="", "SIN RUBRO", VLOOKUP(A12, 'Base 3F'!$B:$J, 9, FALSE))) -> Química | D12: gerencia@aditivosplasticos.com | E12: Principal | F12: funcional
A13: AFONSO GARCIA GONZALO JAVIER (SOLUPLEX) | B13: =IF(A13="", "", IF(IFERROR(VLOOKUP(A13, 'Base 3F'!$B:$C, 2, FALSE),"")="", "SIN CUIT", VLOOKUP(A13, 'Base 3F'!$B:$C, 2, FALSE))) -> 20262813720 | C13: =IF(A13="", "", IF(IFERROR(VLOOKUP(A13, 'Base 3F'!$B:$J, 9, FALSE),"")="", "SIN RUBRO", VLOOKUP(A13, 'Base 3F'!$B:$J, 9, FALSE))) -> Plástica | D13: gafonso@soluplex.com | E13: Principal | F13: funcional
A14: AG METALURGICA S.A. | B14: =IF(A14="", "", IF(IFERROR(VLOOKUP(A14, 'Base 3F'!$B:$C, 2, FALSE),"")="", "SIN CUIT", VLOOKUP(A14, 'Base 3F'!$B:$C, 2, FALSE))) -> 30712300023 | C14: =IF(A14="", "", IF(IFERROR(VLOOKUP(A14, 'Base 3F'!$B:$J, 9, FALSE),"")="", "SIN RUBRO", VLOOKUP(A14, 'Base 3F'!$B:$J, 9, FALSE))) -> Metalmecánica | D14: eduardo@agmetalurgica.com.ar | E14: Principal | F14: funcional
A15: AIMAN S.A. | B15: =IF(A15="", "", IF(IFERROR(VLOOKUP(A15, 'Base 3F'!$B:$C, 2, FALSE),"")="", "SIN CUIT", VLOOKUP(A15, 'Base 3F'!$B:$C, 2, FALSE))) -> 33646972979 | C15: =IF(A15="", "", IF(IFERROR(VLOOKUP(A15, 'Base 3F'!$B:$J, 9, FALSE),"")="", "SIN RUBRO", VLOOKUP(A15, 'Base 3F'!$B:$J, 9, FALSE))) -> Textil | D15: r-roussilian@aiman-sa.com | E15: Principal | F15: funcional
A16: ALAMBRES INDUSTRIALES TREFILADOS S.R.L. (ACEROS VILLA BOSCH S.A.) | B16: =IF(A16="", "", IF(IFERROR(VLOOKUP(A16, 'Base 3F'!$B:$C, 2, FALSE),"")="", "SIN CUIT", VLOOKUP(A16, 'Base 3F'!$B:$C, 2, FALSE))) -> 30647279909 | C16: =IF(A16="", "", IF(IFERROR(VLOOKUP(A16, 'Base 3F'!$B:$J, 9, FALSE),"")="", "SIN RUBRO", VLOOKUP(A16, 'Base 3F'!$B:$J, 9, FALSE))) -> Metalúrgica | D16: andrescz@acerosbosch.com.ar | E16: Principal | F16: funcional
A17: ALBALONGA S.A. | B17: =IF(A17="", "", IF(IFERROR(VLOOKUP(A17, 'Base 3F'!$B:$C, 2, FALSE),"")="", "SIN CUIT", VLOOKUP(A17, 'Base 3F'!$B:$C, 2, FALSE))) -> 30595286189 | C17: =IF(A17="", "", IF(IFERROR(VLOOKUP(A17, 'Base 3F'!$B:$J, 9, FALSE),"")="", "SIN RUBRO", VLOOKUP(A17, 'Base 3F'!$B:$J, 9, FALSE))) -> Textil | D17: disegno.albalonga@gmail.com | E17: Principal | F17: funcional
A18: ALFONSO SABBATINI E HIJO S.R.L. | B18: =IF(A18="", "", IF(IFERROR(VLOOKUP(A18, 'Base 3F'!$B:$C, 2, FALSE),"")="", "SIN CUIT", VLOOKUP(A18, 'Base 3F'!$B:$C, 2, FALSE))) -> 30709636991 | C18: =IF(A18="", "", IF(IFERROR(VLOOKUP(A18, 'Base 3F'!$B:$J, 9, FALSE),"")="", "SIN RUBRO", VLOOKUP(A18, 'Base 3F'!$B:$J, 9, FALSE))) -> Metalúrgica | D18: alejandro@sabbatini.com.ar | E18: Principal | F18: funcional
A19: ALFONSO SABBATINI E HIJO S.R.L. | B19: =IF(A19="", "", IF(IFERROR(VLOOKUP(A19, 'Base 3F'!$B:$C, 2, FALSE),"")="", "SIN CUIT", VLOOKUP(A19, 'Base 3F'!$B:$C, 2, FALSE))) -> 30709636991 | C19: =IF(A19="", "", IF(IFERROR(VLOOKUP(A19, 'Base 3F'!$B:$J, 9, FALSE),"")="", "SIN RUBRO", VLOOKUP(A19, 'Base 3F'!$B:$J, 9, FALSE))) -> Metalúrgica | D19: eduardo@sabbatini.com.ar | E19: Principal | F19: funcional
A20: ALIMENTOS AGRELE S.R.L. (CRISPPINO) | B20: =IF(A20="", "", IF(IFERROR(VLOOKUP(A20, 'Base 3F'!$B:$C, 2, FALSE),"")="", "SIN CUIT", VLOOKUP(A20, 'Base 3F'!$B:$C, 2, FALSE))) -> 30714502367 | C20: =IF(A20="", "", IF(IFERROR(VLOOKUP(A20, 'Base 3F'!$B:$J, 9, FALSE),"")="", "SIN RUBRO", VLOOKUP(A20, 'Base 3F'!$B:$J, 9, FALSE))) -> Alimenticia | D20: oliver@crisppino.com | E20: Principal | F20: funcional
... A417: BRAGA ALICIA BEATRIZ ( METALURGICA JORGE) | B417: =IF(A417="", "", IF(IFERROR(VLOOKUP(A417, 'Base 3F'!$B:$C, 2, FALSE),"")="", "SIN CUIT", VLOOKUP(A417, 'Base 3F'!$B:$C, 2, FALSE))) -> 27119119907 | C417: =IF(A417="", "", IF(IFERROR(VLOOKUP(A417, 'Base 3F'!$B:$J, 9, FALSE),"")="", "SIN RUBRO", VLOOKUP(A417, 'Base 3F'!$B:$J, 9, FALSE))) -> Metalúrgica | D417: metalurgicajorge@hotmail.com | E417: Secundario | F417: funcional
A418: INDUSTRIA METALURGICA LH S.R.L.- | B418: 33717414379 | C418: =IF(A418="", "", IF(IFERROR(VLOOKUP(A418, 'Base 3F'!$B:$J, 9, FALSE),"")="", "SIN RUBRO", VLOOKUP(A418, 'Base 3F'!$B:$J, 9, FALSE))) -> Metalúrgica | D418: info@metalurgica-lh.com.ar | E418: Secundario | F418: rebotado_desconocido
A419: PANDIANI WALTER HUGO | B419: =IF(A419="", "", IF(IFERROR(VLOOKUP(A419, 'Base 3F'!$B:$C, 2, FALSE),"")="", "SIN CUIT", VLOOKUP(A419, 'Base 3F'!$B:$C, 2, FALSE))) -> 20227214865 | C419: =IF(A419="", "", IF(IFERROR(VLOOKUP(A419, 'Base 3F'!$B:$J, 9, FALSE),"")="", "SIN RUBRO", VLOOKUP(A419, 'Base 3F'!$B:$J, 9, FALSE))) -> Alimenticia | D419: nm.condimentos@gmail.com | E419: Secundario | F419: funcional
A420: ALCOBENDAS SA- | B420: =IF(A420="", "", IF(IFERROR(VLOOKUP(A420, 'Base 3F'!$B:$C, 2, FALSE),"")="", "SIN CUIT", VLOOKUP(A420, 'Base 3F'!$B:$C, 2, FALSE))) -> 30717619753 | C420: =IF(A420="", "", IF(IFERROR(VLOOKUP(A420, 'Base 3F'!$B:$J, 9, FALSE),"")="", "SIN RUBRO", VLOOKUP(A420, 'Base 3F'!$B:$J, 9, FALSE))) -> Alimenticia | D420: madubovsky@gmail.com | E420: Secundario | F420: rebotado_spam
A421: FACCIOPANE S.R.L. | B421: =IF(A421="", "", IF(IFERROR(VLOOKUP(A421, 'Base 3F'!$B:$C, 2, FALSE),"")="", "SIN CUIT", VLOOKUP(A421, 'Base 3F'!$B:$C, 2, FALSE))) -> 30715604635 | C421: =IF(A421="", "", IF(IFERROR(VLOOKUP(A421, 'Base 3F'!$B:$J, 9, FALSE),"")="", "SIN RUBRO", VLOOKUP(A421, 'Base 3F'!$B:$J, 9, FALSE))) -> Alimenticia | D421: ksedani@sgestiongroup.com | E421: Secundario | F421: funcional
A422: IANNELLO, GUSTAVO DOMINGO | B422: =IF(A422="", "", IF(IFERROR(VLOOKUP(A422, 'Base 3F'!$B:$C, 2, FALSE),"")="", "SIN CUIT", VLOOKUP(A422, 'Base 3F'!$B:$C, 2, FALSE))) -> 20308378498 | C422: =IF(A422="", "", IF(IFERROR(VLOOKUP(A422, 'Base 3F'!$B:$J, 9, FALSE),"")="", "SIN RUBRO", VLOOKUP(A422, 'Base 3F'!$B:$J, 9, FALSE))) -> Química | D422: gustavoiannello1984@gmail.com | E422: Secundario | F422: funcional
A423: ALEMAN NORA MIRTA | B423: =IF(A423="", "", IF(IFERROR(VLOOKUP(A423, 'Base 3F'!$B:$C, 2, FALSE),"")="", "SIN CUIT", VLOOKUP(A423, 'Base 3F'!$B:$C, 2, FALSE))) -> 27052789597 | C423: =IF(A423="", "", IF(IFERROR(VLOOKUP(A423, 'Base 3F'!$B:$J, 9, FALSE),"")="", "SIN RUBRO", VLOOKUP(A423, 'Base 3F'!$B:$J, 9, FALSE))) -> Electrónica | D423: va70oviedo@gmail.com | E423: Secundario | F423: funcional
A424: GIANNECCHINI VICTOR MATIAS | B424: =IF(A424="", "", IF(IFERROR(VLOOKUP(A424, 'Base 3F'!$B:$C, 2, FALSE),"")="", "SIN CUIT", VLOOKUP(A424, 'Base 3F'!$B:$C, 2, FALSE))) -> 20359896000 | C424: =IF(A424="", "", IF(IFERROR(VLOOKUP(A424, 'Base 3F'!$B:$J, 9, FALSE),"")="", "SIN RUBRO", VLOOKUP(A424, 'Base 3F'!$B:$J, 9, FALSE))) -> Plástica | D424: matiasgiomecchini@gmail.com | E424: Secundario | F424: funcional
A425: MOGNI JOSE LUIS | B425: =IF(A425="", "", IF(IFERROR(VLOOKUP(A425, 'Base 3F'!$B:$C, 2, FALSE),"")="", "SIN CUIT", VLOOKUP(A425, 'Base 3F'!$B:$C, 2, FALSE))) -> 20176021714 | C425: =IF(A425="", "", IF(IFERROR(VLOOKUP(A425, 'Base 3F'!$B:$J, 9, FALSE),"")="", "SIN RUBRO", VLOOKUP(A425, 'Base 3F'!$B:$J, 9, FALSE))) -> Metalúrgica | D425: JOSELMOGNI@HOTMAIL.COM | E425: Secundario | F425: funcional
A426: CARDOZO JOSE LUIS, ESPLUGAS FRANCISCO JOSE, DIAZ MANUEL, DIAZ FERNANDO SOCIEDAD DE HECHO | B426: =IF(A426="", "", IF(IFERROR(VLOOKUP(A426, 'Base 3F'!$B:$C, 2, FALSE),"")="", "SIN CUIT", VLOOKUP(A426, 'Base 3F'!$B:$C, 2, FALSE))) -> 30712373047 | C426: =IF(A426="", "", IF(IFERROR(VLOOKUP(A426, 'Base 3F'!$B:$J, 9, FALSE),"")="", "SIN RUBRO", VLOOKUP(A426, 'Base 3F'!$B:$J, 9, FALSE))) -> Madera | D426: alriomultilaminados@hotmail.com | E426: Secundario | F426: funcional
A427: DE NUNZIO JUAN PABLO | B427: =IF(A427="", "", IF(IFERROR(VLOOKUP(A427, 'Base 3F'!$B:$C, 2, FALSE),"")="", "SIN CUIT", VLOOKUP(A427, 'Base 3F'!$B:$C, 2, FALSE))) -> 20288571571 | C427: =IF(A427="", "", IF(IFERROR(VLOOKUP(A427, 'Base 3F'!$B:$J, 9, FALSE),"")="", "SIN RUBRO", VLOOKUP(A427, 'Base 3F'!$B:$J, 9, FALSE))) -> Madera | D427: jpablodn@hotmail.com | E427: Secundario | F427: funcional
A428: GROUNDNUT S.R.L. | B428: =IF(A428="", "", IF(IFERROR(VLOOKUP(A428, 'Base 3F'!$B:$C, 2, FALSE),"")="", "SIN CUIT", VLOOKUP(A428, 'Base 3F'!$B:$C, 2, FALSE))) -> 30717389529 | C428: =IF(A428="", "", IF(IFERROR(VLOOKUP(A428, 'Base 3F'!$B:$J, 9, FALSE),"")="", "SIN RUBRO", VLOOKUP(A428, 'Base 3F'!$B:$J, 9, FALSE))) -> Alimenticia | D428: hdimecola@hotmail.com | E428: Secundario | F428: funcional
A429: HERMETICA P.V.C S.R.L | B429: =IF(A429="", "", IF(IFERROR(VLOOKUP(A429, 'Base 3F'!$B:$C, 2, FALSE),"")="", "SIN CUIT", VLOOKUP(A429, 'Base 3F'!$B:$C, 2, FALSE))) -> 33716790369 | C429: =IF(A429="", "", IF(IFERROR(VLOOKUP(A429, 'Base 3F'!$B:$J, 9, FALSE),"")="", "SIN RUBRO", VLOOKUP(A429, 'Base 3F'!$B:$J, 9, FALSE))) -> Metalúrgica | D429: hermeticapvc@gmail.com | E429: Secundario | F429: funcional
A430: NINA LLANQUE VIDAL | B430: =IF(A430="", "", IF(IFERROR(VLOOKUP(A430, 'Base 3F'!$B:$C, 2, FALSE),"")="", "SIN CUIT", VLOOKUP(A430, 'Base 3F'!$B:$C, 2, FALSE))) -> 20940698198 | C430: =IF(A430="", "", IF(IFERROR(VLOOKUP(A430, 'Base 3F'!$B:$J, 9, FALSE),"")="", "SIN RUBRO", VLOOKUP(A430, 'Base 3F'!$B:$J, 9, FALSE))) -> Textil | D430: nina_09ldz@live.com.ar | E430: Secundario | F430: funcional
... A534: PROCESADORA ASAMBLEA S.A- | B534: =IF(A534="", "", IF(IFERROR(VLOOKUP(A534, 'Base 3F'!$B:$C, 2, FALSE),"")="", "SIN CUIT", VLOOKUP(A534, 'Base 3F'!$B:$C, 2, FALSE))) -> 30708070994 | C534: =IF(A534="", "", IF(IFERROR(VLOOKUP(A534, 'Base 3F'!$B:$J, 9, FALSE),"")="", "SIN RUBRO", VLOOKUP(A534, 'Base 3F'!$B:$J, 9, FALSE))) -> Servicios | D534: procesadorajeans@gmail.com | E534: Secundario | F534: funcional
A535: PROFILES ACEROS S.A | B535: =IF(A535="", "", IF(IFERROR(VLOOKUP(A535, 'Base 3F'!$B:$C, 2, FALSE),"")="", "SIN CUIT", VLOOKUP(A535, 'Base 3F'!$B:$C, 2, FALSE))) -> 30714419362 | C535: =IF(A535="", "", IF(IFERROR(VLOOKUP(A535, 'Base 3F'!$B:$J, 9, FALSE),"")="", "SIN RUBRO", VLOOKUP(A535, 'Base 3F'!$B:$J, 9, FALSE))) -> Metalúrgica | D535: profilesaceros@gmail.com | E535: Secundario | F535: funcional | G535: ssss
A536: ACEROS COFER S.A. | B536: =IF(A536="", "", IF(IFERROR(VLOOKUP(A536, 'Base 3F'!$B:$C, 2, FALSE),"")="", "SIN CUIT", VLOOKUP(A536, 'Base 3F'!$B:$C, 2, FALSE))) -> 30707576444 | C536: =IF(A536="", "", IF(IFERROR(VLOOKUP(A536, 'Base 3F'!$B:$J, 9, FALSE),"")="", "SIN RUBRO", VLOOKUP(A536, 'Base 3F'!$B:$J, 9, FALSE))) -> Metalúrgica | D536: aceroscofer@aceroscofer.com.ar | E536: Secundario | F536: funcional
A537: ACEROS MB S.A. | B537: =IF(A537="", "", IF(IFERROR(VLOOKUP(A537, 'Base 3F'!$B:$C, 2, FALSE),"")="", "SIN CUIT", VLOOKUP(A537, 'Base 3F'!$B:$C, 2, FALSE))) -> 30584398694 | C537: =IF(A537="", "", IF(IFERROR(VLOOKUP(A537, 'Base 3F'!$B:$J, 9, FALSE),"")="", "SIN RUBRO", VLOOKUP(A537, 'Base 3F'!$B:$J, 9, FALSE))) -> Metalúrgica | D537: jpmontan@acerosmb.com.ar | E537: Secundario | F537: funcional
A538: ACRILICOS AMENDOLA MARIANI S.R.L. | B538: =IF(A538="", "", IF(IFERROR(VLOOKUP(A538, 'Base 3F'!$B:$C, 2, FALSE),"")="", "SIN CUIT", VLOOKUP(A538, 'Base 3F'!$B:$C, 2, FALSE))) -> 30647516366 | C538: =IF(A538="", "", IF(IFERROR(VLOOKUP(A538, 'Base 3F'!$B:$J, 9, FALSE),"")="", "SIN RUBRO", VLOOKUP(A538, 'Base 3F'!$B:$J, 9, FALSE))) -> Plástica | D538: acrilicosamendolamariani@gmail.com | E538: Secundario | F538: funcional
A539: ACYTRA SAIC S.A. | B539: =IF(A539="", "", IF(IFERROR(VLOOKUP(A539, 'Base 3F'!$B:$C, 2, FALSE),"")="", "SIN CUIT", VLOOKUP(A539, 'Base 3F'!$B:$C, 2, FALSE))) -> 30502185787 | C539: =IF(A539="", "", IF(IFERROR(VLOOKUP(A539, 'Base 3F'!$B:$J, 9, FALSE),"")="", "SIN RUBRO", VLOOKUP(A539, 'Base 3F'!$B:$J, 9, FALSE))) -> Metalúrgica | D539: lacoppma@acytra.com | E539: Secundario | F539: funcional
A540: AFONSO GARCIA GONZALO JAVIER (SOLUPLEX) | B540: =IF(A540="", "", IF(IFERROR(VLOOKUP(A540, 'Base 3F'!$B:$C, 2, FALSE),"")="", "SIN CUIT", VLOOKUP(A540, 'Base 3F'!$B:$C, 2, FALSE))) -> 20262813720 | C540: =IF(A540="", "", IF(IFERROR(VLOOKUP(A540, 'Base 3F'!$B:$J, 9, FALSE),"")="", "SIN RUBRO", VLOOKUP(A540, 'Base 3F'!$B:$J, 9, FALSE))) -> Plástica | D540: rbesteiro@soluplex.com | E540: Secundario | F540: funcional
A541: AFTYKA SACHON INDUSTRIAS S.R.L. (AS INDUSTRIAS) | B541: =IF(A541="", "", IF(IFERROR(VLOOKUP(A541, 'Base 3F'!$B:$C, 2, FALSE),"")="", "SIN CUIT", VLOOKUP(A541, 'Base 3F'!$B:$C, 2, FALSE))) -> 33708183909 | C541: =IF(A541="", "", IF(IFERROR(VLOOKUP(A541, 'Base 3F'!$B:$J, 9, FALSE),"")="", "SIN RUBRO", VLOOKUP(A541, 'Base 3F'!$B:$J, 9, FALSE))) -> Caucho | D541: info@asindustrias.com.ar | E541: Secundario | F541: funcional
A542: ALAMBRES INDUSTRIALES TREFILADOS S.R.L. (ACEROS VILLA BOSCH S.A.) | B542: =IF(A542="", "", IF(IFERROR(VLOOKUP(A542, 'Base 3F'!$B:$C, 2, FALSE),"")="", "SIN CUIT", VLOOKUP(A542, 'Base 3F'!$B:$C, 2, FALSE))) -> 30647279909 | C542: =IF(A542="", "", IF(IFERROR(VLOOKUP(A542, 'Base 3F'!$B:$J, 9, FALSE),"")="", "SIN RUBRO", VLOOKUP(A542, 'Base 3F'!$B:$J, 9, FALSE))) -> Metalúrgica | D542: marcelol@acerosbosch.com.ar | E542: Secundario | F542: funcional
A543: ALBALONGA S.A. | B543: =IF(A543="", "", IF(IFERROR(VLOOKUP(A543, 'Base 3F'!$B:$C, 2, FALSE),"")="", "SIN CUIT", VLOOKUP(A543, 'Base 3F'!$B:$C, 2, FALSE))) -> 30595286189 | C543: =IF(A543="", "", IF(IFERROR(VLOOKUP(A543, 'Base 3F'!$B:$J, 9, FALSE),"")="", "SIN RUBRO", VLOOKUP(A543, 'Base 3F'!$B:$J, 9, FALSE))) -> Textil | D543: albalongatextil@gmail.com | E543: Secundario | F543: funcional
A544: ALFONSO SABBATINI E HIJO S.R.L. | B544: =IF(A544="", "", IF(IFERROR(VLOOKUP(A544, 'Base 3F'!$B:$C, 2, FALSE),"")="", "SIN CUIT", VLOOKUP(A544, 'Base 3F'!$B:$C, 2, FALSE))) -> 30709636991 | C544: =IF(A544="", "", IF(IFERROR(VLOOKUP(A544, 'Base 3F'!$B:$J, 9, FALSE),"")="", "SIN RUBRO", VLOOKUP(A544, 'Base 3F'!$B:$J, 9, FALSE))) -> Metalúrgica | D544: comex@sabbatini.com.ar | E544: Secundario | F544: funcional
A545: ALIMENTOS NOLY S. A. (DOÑA NOLY) | B545: =IF(A545="", "", IF(IFERROR(VLOOKUP(A545, 'Base 3F'!$B:$C, 2, FALSE),"")="", "SIN CUIT", VLOOKUP(A545, 'Base 3F'!$B:$C, 2, FALSE))) -> 30583370028 | C545: =IF(A545="", "", IF(IFERROR(VLOOKUP(A545, 'Base 3F'!$B:$J, 9, FALSE),"")="", "SIN RUBRO", VLOOKUP(A545, 'Base 3F'!$B:$J, 9, FALSE))) -> Alimenticia | D545: pvalentino@noly.com.ar | E545: Secundario | F545: funcional
A546: ALIMENTOS SILVA S.A. | B546: =IF(A546="", "", IF(IFERROR(VLOOKUP(A546, 'Base 3F'!$B:$C, 2, FALSE),"")="", "SIN CUIT", VLOOKUP(A546, 'Base 3F'!$B:$C, 2, FALSE))) -> 30710162669 | C546: =IF(A546="", "", IF(IFERROR(VLOOKUP(A546, 'Base 3F'!$B:$J, 9, FALSE),"")="", "SIN RUBRO", VLOOKUP(A546, 'Base 3F'!$B:$J, 9, FALSE))) -> Alimenticia | D546: yanina@distribuciongloball.com | E546: Secundario | F546: funcional
A547: AMENTUEL S.A. | B547: =IF(A547="", "", IF(IFERROR(VLOOKUP(A547, 'Base 3F'!$B:$C, 2, FALSE),"")="", "SIN CUIT", VLOOKUP(A547, 'Base 3F'!$B:$C, 2, FALSE))) -> 30691156377 | C547: =IF(A547="", "", IF(IFERROR(VLOOKUP(A547, 'Base 3F'!$B:$J, 9, FALSE),"")="", "SIN RUBRO", VLOOKUP(A547, 'Base 3F'!$B:$J, 9, FALSE))) -> Alimenticia | D547: daniel@amentuel.com.ar | E547: Secundario | F547: funcional
... A598: ETC S.A. | B598: =IF(A598="", "", IF(IFERROR(VLOOKUP(A598, 'Base 3F'!$B:$C, 2, FALSE),"")="", "SIN CUIT", VLOOKUP(A598, 'Base 3F'!$B:$C, 2, FALSE))) -> 33644120479 | C598: =IF(A598="", "", IF(IFERROR(VLOOKUP(A598, 'Base 3F'!$B:$J, 9, FALSE),"")="", "SIN RUBRO", VLOOKUP(A598, 'Base 3F'!$B:$J, 9, FALSE))) -> Metalúrgica | D598: liliana@etc.com.ar | E598: Secundario | F598: funcional
A599: EXERT ARGENTINA S.R.L. | B599: 30708856653 | C599: =IF(A599="", "", IF(IFERROR(VLOOKUP(A599, 'Base 3F'!$B:$J, 9, FALSE),"")="", "SIN RUBRO", VLOOKUP(A599, 'Base 3F'!$B:$J, 9, FALSE))) -> Servicios | D599: exertsrl@exertsrl.com.ar | E599: Secundario | F599: rebotado_desconocido
A600: FDM S.R.L. | B600: =IF(A600="", "", IF(IFERROR(VLOOKUP(A600, 'Base 3F'!$B:$C, 2, FALSE),"")="", "SIN CUIT", VLOOKUP(A600, 'Base 3F'!$B:$C, 2, FALSE))) -> 30677077596 | C600: =IF(A600="", "", IF(IFERROR(VLOOKUP(A600, 'Base 3F'!$B:$J, 9, FALSE),"")="", "SIN RUBRO", VLOOKUP(A600, 'Base 3F'!$B:$J, 9, FALSE))) -> Metalúrgica | D600: miguelina@fdm-srl.com.ar | E600: Secundario | F600: funcional
A601: FE PUBLICIDAD ARGENTINA S.A. | B601: =IF(A601="", "", IF(IFERROR(VLOOKUP(A601, 'Base 3F'!$B:$C, 2, FALSE),"")="", "SIN CUIT", VLOOKUP(A601, 'Base 3F'!$B:$C, 2, FALSE))) -> 30710218486 | C601: =IF(A601="", "", IF(IFERROR(VLOOKUP(A601, 'Base 3F'!$B:$J, 9, FALSE),"")="", "SIN RUBRO", VLOOKUP(A601, 'Base 3F'!$B:$J, 9, FALSE))) -> Gráfica | D601: lilianapanighetto@fepublicidad.com.ar | E601: Secundario | F601: funcional
A602: FERCOR FIJACIONES S.R.L. | B602: =IF(A602="", "", IF(IFERROR(VLOOKUP(A602, 'Base 3F'!$B:$C, 2, FALSE),"")="", "SIN CUIT", VLOOKUP(A602, 'Base 3F'!$B:$C, 2, FALSE))) -> 30709190713 | C602: =IF(A602="", "", IF(IFERROR(VLOOKUP(A602, 'Base 3F'!$B:$J, 9, FALSE),"")="", "SIN RUBRO", VLOOKUP(A602, 'Base 3F'!$B:$J, 9, FALSE))) -> Metalúrgica | D602: jgonzalez@fercor.com.ar | E602: Secundario | F602: funcional
A603: FLEJIE S.R.L. | B603: =IF(A603="", "", IF(IFERROR(VLOOKUP(A603, 'Base 3F'!$B:$C, 2, FALSE),"")="", "SIN CUIT", VLOOKUP(A603, 'Base 3F'!$B:$C, 2, FALSE))) -> 30685329502 | C603: =IF(A603="", "", IF(IFERROR(VLOOKUP(A603, 'Base 3F'!$B:$J, 9, FALSE),"")="", "SIN RUBRO", VLOOKUP(A603, 'Base 3F'!$B:$J, 9, FALSE))) -> Manufactura | D603: flejie_sanmartin@hotmail.com | E603: Secundario | F603: funcional
A604: FRENOS NACIONALES S.A. | B604: =IF(A604="", "", IF(IFERROR(VLOOKUP(A604, 'Base 3F'!$B:$C, 2, FALSE),"")="", "SIN CUIT", VLOOKUP(A604, 'Base 3F'!$B:$C, 2, FALSE))) -> 30709052442 | C604: =IF(A604="", "", IF(IFERROR(VLOOKUP(A604, 'Base 3F'!$B:$J, 9, FALSE),"")="", "SIN RUBRO", VLOOKUP(A604, 'Base 3F'!$B:$J, 9, FALSE))) -> Metalmecánica | D604: administracion@frenosnacionales.com.ar | E604: Secundario | F604: funcional
A605: FRIGORÍFICO POCKER S.A. | B605: =IF(A605="", "", IF(IFERROR(VLOOKUP(A605, 'Base 3F'!$B:$C, 2, FALSE),"")="", "SIN CUIT", VLOOKUP(A605, 'Base 3F'!$B:$C, 2, FALSE))) -> 30707422099 | C605: =IF(A605="", "", IF(IFERROR(VLOOKUP(A605, 'Base 3F'!$B:$J, 9, FALSE),"")="", "SIN RUBRO", VLOOKUP(A605, 'Base 3F'!$B:$J, 9, FALSE))) -> Alimenticia | D605: ivanlopesrito16@gmail.com | E605: Secundario | F605: funcional
A606: FRIONE S.R.L. | B606: =IF(A606="", "", IF(IFERROR(VLOOKUP(A606, 'Base 3F'!$B:$C, 2, FALSE),"")="", "SIN CUIT", VLOOKUP(A606, 'Base 3F'!$B:$C, 2, FALSE))) -> 30708866608 | C606: =IF(A606="", "", IF(IFERROR(VLOOKUP(A606, 'Base 3F'!$B:$J, 9, FALSE),"")="", "SIN RUBRO", VLOOKUP(A606, 'Base 3F'!$B:$J, 9, FALSE))) -> Textil | D606: claudio@frione.com | E606: Secundario | F606: funcional
A607: FULL PLASTICS S.A. | B607: =IF(A607="", "", IF(IFERROR(VLOOKUP(A607, 'Base 3F'!$B:$C, 2, FALSE),"")="", "SIN CUIT", VLOOKUP(A607, 'Base 3F'!$B:$C, 2, FALSE))) -> 30709239305 | C607: =IF(A607="", "", IF(IFERROR(VLOOKUP(A607, 'Base 3F'!$B:$J, 9, FALSE),"")="", "SIN RUBRO", VLOOKUP(A607, 'Base 3F'!$B:$J, 9, FALSE))) -> Plástica | D607: grinaldi@fullplastics.com.ar | E607: Secundario | F607: funcional
A608: GALILEO TECHNOLOGIES S.A. | B608: =IF(A608="", "", IF(IFERROR(VLOOKUP(A608, 'Base 3F'!$B:$C, 2, FALSE),"")="", "SIN CUIT", VLOOKUP(A608, 'Base 3F'!$B:$C, 2, FALSE))) -> 30628418329 | C608: =IF(A608="", "", IF(IFERROR(VLOOKUP(A608, 'Base 3F'!$B:$J, 9, FALSE),"")="", "SIN RUBRO", VLOOKUP(A608, 'Base 3F'!$B:$J, 9, FALSE))) -> Metalúrgica | D608: rdesimone@galileoar.com | E608: Secundario | F608: funcional
A609: GALVYLAM S.A. | B609: =IF(A609="", "", IF(IFERROR(VLOOKUP(A609, 'Base 3F'!$B:$C, 2, FALSE),"")="", "SIN CUIT", VLOOKUP(A609, 'Base 3F'!$B:$C, 2, FALSE))) -> 30701149579 | C609: =IF(A609="", "", IF(IFERROR(VLOOKUP(A609, 'Base 3F'!$B:$J, 9, FALSE),"")="", "SIN RUBRO", VLOOKUP(A609, 'Base 3F'!$B:$J, 9, FALSE))) -> Metalúrgica | D609: administracion1@galvylam.com | E609: Secundario | F609: funcional
A610: GAMUZA HOGAR S.A. | B610: =IF(A610="", "", IF(IFERROR(VLOOKUP(A610, 'Base 3F'!$B:$C, 2, FALSE),"")="", "SIN CUIT", VLOOKUP(A610, 'Base 3F'!$B:$C, 2, FALSE))) -> 30714743062 | C610: =IF(A610="", "", IF(IFERROR(VLOOKUP(A610, 'Base 3F'!$B:$J, 9, FALSE),"")="", "SIN RUBRO", VLOOKUP(A610, 'Base 3F'!$B:$J, 9, FALSE))) -> Metalúrgica | D610: claudiocardinali25@gmail.com | E610: Secundario | F610: funcional
A611: GIGANTOGRAFICA S.A. | B611: =IF(A611="", "", IF(IFERROR(VLOOKUP(A611, 'Base 3F'!$B:$C, 2, FALSE),"")="", "SIN CUIT", VLOOKUP(A611, 'Base 3F'!$B:$C, 2, FALSE))) -> 30691261677 | C611: =IF(A611="", "", IF(IFERROR(VLOOKUP(A611, 'Base 3F'!$B:$J, 9, FALSE),"")="", "SIN RUBRO", VLOOKUP(A611, 'Base 3F'!$B:$J, 9, FALSE))) -> Servicios | D611: o.suarez@gigantografica.com | E611: Secundario | F611: funcional
... A710: FERREIRO MARIANO JAVIER (Bulonería MaFerBul) | B710: =IF(A710="", "", IF(IFERROR(VLOOKUP(A710, 'Base 3F'!$B:$C, 2, FALSE),"")="", "SIN CUIT", VLOOKUP(A710, 'Base 3F'!$B:$C, 2, FALSE))) -> 20308332323 | C710: =IF(A710="", "", IF(IFERROR(VLOOKUP(A710, 'Base 3F'!$B:$J, 9, FALSE),"")="", "SIN RUBRO", VLOOKUP(A710, 'Base 3F'!$B:$J, 9, FALSE))) -> Metalúrgica | D710: info@maferbul.com.ar | E710: Secundario | F710: funcional
A711: 1989 ESTUDIO A S.R.L. | ALEJANDRO Y MIGUEL ANGEL RIZZI S.H. | B711: =IF(A711="", "", IF(IFERROR(VLOOKUP(A711, 'Base 3F'!$B:$C, 2, FALSE),"")="", "SIN CUIT", VLOOKUP(A711, 'Base 3F'!$B:$C, 2, FALSE))) -> 30709328995 | 30710682816 | C711: =IF(A711="", "", IF(IFERROR(VLOOKUP(A711, 'Base 3F'!$B:$J, 9, FALSE),"")="", "SIN RUBRO", VLOOKUP(A711, 'Base 3F'!$B:$J, 9, FALSE))) -> Papel | D711: administracion@estudioapop.com.ar | E711: Secundario | F711: funcional | G711: ddd
A712: 2G ADHESIVOS S.R.L. | B712: =IF(A712="", "", IF(IFERROR(VLOOKUP(A712, 'Base 3F'!$B:$C, 2, FALSE),"")="", "SIN CUIT", VLOOKUP(A712, 'Base 3F'!$B:$C, 2, FALSE))) -> 30714815179 | C712: =IF(A712="", "", IF(IFERROR(VLOOKUP(A712, 'Base 3F'!$B:$J, 9, FALSE),"")="", "SIN RUBRO", VLOOKUP(A712, 'Base 3F'!$B:$J, 9, FALSE))) -> Química | D712: info@dosg.com.ar | E712: Secundario | F712: funcional
A713: A D S.A. | B713: =IF(A713="", "", IF(IFERROR(VLOOKUP(A713, 'Base 3F'!$B:$C, 2, FALSE),"")="", "SIN CUIT", VLOOKUP(A713, 'Base 3F'!$B:$C, 2, FALSE))) -> 30710393725 | C713: =IF(A713="", "", IF(IFERROR(VLOOKUP(A713, 'Base 3F'!$B:$J, 9, FALSE),"")="", "SIN RUBRO", VLOOKUP(A713, 'Base 3F'!$B:$J, 9, FALSE))) -> Metalúrgica | D713: recepcion@amasd.com.ar | E713: Secundario | F713: funcional
A714: A PATKO Y CIA S.A. | B714: =IF(A714="", "", IF(IFERROR(VLOOKUP(A714, 'Base 3F'!$B:$C, 2, FALSE),"")="", "SIN CUIT", VLOOKUP(A714, 'Base 3F'!$B:$C, 2, FALSE))) -> 30518263834 | C714: =IF(A714="", "", IF(IFERROR(VLOOKUP(A714, 'Base 3F'!$B:$J, 9, FALSE),"")="", "SIN RUBRO", VLOOKUP(A714, 'Base 3F'!$B:$J, 9, FALSE))) -> Metalúrgica | D714: christianpatko@hotmail.com | E714: Secundario | F714: funcional
A715: AANTAJ S.R.L. | B715: =IF(A715="", "", IF(IFERROR(VLOOKUP(A715, 'Base 3F'!$B:$C, 2, FALSE),"")="", "SIN CUIT", VLOOKUP(A715, 'Base 3F'!$B:$C, 2, FALSE))) -> 30709992178 | C715: =IF(A715="", "", IF(IFERROR(VLOOKUP(A715, 'Base 3F'!$B:$J, 9, FALSE),"")="", "SIN RUBRO", VLOOKUP(A715, 'Base 3F'!$B:$J, 9, FALSE))) -> Textil | D715: aantaj@aantaj.com.ar | E715: Secundario | F715: funcional
A716: ABAFLEX S.A. | B716: =IF(A716="", "", IF(IFERROR(VLOOKUP(A716, 'Base 3F'!$B:$C, 2, FALSE),"")="", "SIN CUIT", VLOOKUP(A716, 'Base 3F'!$B:$C, 2, FALSE))) -> 30597429130 | C716: =IF(A716="", "", IF(IFERROR(VLOOKUP(A716, 'Base 3F'!$B:$J, 9, FALSE),"")="", "SIN RUBRO", VLOOKUP(A716, 'Base 3F'!$B:$J, 9, FALSE))) -> Plástica | D716: info@abaflex.com.ar | E716: Secundario | F716: funcional
A717: ABBOMAR S.A. | B717: =IF(A717="", "", IF(IFERROR(VLOOKUP(A717, 'Base 3F'!$B:$C, 2, FALSE),"")="", "SIN CUIT", VLOOKUP(A717, 'Base 3F'!$B:$C, 2, FALSE))) -> 30710802552 | C717: =IF(A717="", "", IF(IFERROR(VLOOKUP(A717, 'Base 3F'!$B:$J, 9, FALSE),"")="", "SIN RUBRO", VLOOKUP(A717, 'Base 3F'!$B:$J, 9, FALSE))) -> Construcción | D717: abbomar.abbomar@gmail.com | E717: Secundario | F717: funcional
A718: ABELARDO ESTEBAN (VALVULAS ESTEBAN) | B718: =IF(A718="", "", IF(IFERROR(VLOOKUP(A718, 'Base 3F'!$B:$C, 2, FALSE),"")="", "SIN CUIT", VLOOKUP(A718, 'Base 3F'!$B:$C, 2, FALSE))) -> 20105339330 | C718: =IF(A718="", "", IF(IFERROR(VLOOKUP(A718, 'Base 3F'!$B:$J, 9, FALSE),"")="", "SIN RUBRO", VLOOKUP(A718, 'Base 3F'!$B:$J, 9, FALSE))) -> Metalúrgica | D718: cynthia@valvulas-esteban.com.ar | E718: Secundario | F718: funcional
A719: ABERMATIC S.R.L. | B719: =IF(A719="", "", IF(IFERROR(VLOOKUP(A719, 'Base 3F'!$B:$C, 2, FALSE),"")="", "SIN CUIT", VLOOKUP(A719, 'Base 3F'!$B:$C, 2, FALSE))) -> 30707243844 | C719: =IF(A719="", "", IF(IFERROR(VLOOKUP(A719, 'Base 3F'!$B:$J, 9, FALSE),"")="", "SIN RUBRO", VLOOKUP(A719, 'Base 3F'!$B:$J, 9, FALSE))) -> Metalúrgica | D719: abermatic@abermatic.com | E719: Secundario | F719: funcional
A720: ABK SOCIEDAD DE RESPONSABILIDAD LIMITADA | B720: =IF(A720="", "", IF(IFERROR(VLOOKUP(A720, 'Base 3F'!$B:$C, 2, FALSE),"")="", "SIN CUIT", VLOOKUP(A720, 'Base 3F'!$B:$C, 2, FALSE))) -> 33625752499 | C720: =IF(A720="", "", IF(IFERROR(VLOOKUP(A720, 'Base 3F'!$B:$J, 9, FALSE),"")="", "SIN RUBRO", VLOOKUP(A720, 'Base 3F'!$B:$J, 9, FALSE))) -> Química | D720: abk@abk.com.ar | E720: Secundario | F720: funcional
A721: ACCECUER S.A. | B721: =IF(A721="", "", IF(IFERROR(VLOOKUP(A721, 'Base 3F'!$B:$C, 2, FALSE),"")="", "SIN CUIT", VLOOKUP(A721, 'Base 3F'!$B:$C, 2, FALSE))) -> 30632566448 | C721: =IF(A721="", "", IF(IFERROR(VLOOKUP(A721, 'Base 3F'!$B:$J, 9, FALSE),"")="", "SIN RUBRO", VLOOKUP(A721, 'Base 3F'!$B:$J, 9, FALSE))) -> Cuero | D721: producto@accecuer.com.ar | E721: Secundario | F721: funcional
A722: ACEROS ACEPER DE DALL ASTA CLAUDIA VIVIANA | B722: =IF(A722="", "", IF(IFERROR(VLOOKUP(A722, 'Base 3F'!$B:$C, 2, FALSE),"")="", "SIN CUIT", VLOOKUP(A722, 'Base 3F'!$B:$C, 2, FALSE))) -> 27162030618 | C722: =IF(A722="", "", IF(IFERROR(VLOOKUP(A722, 'Base 3F'!$B:$J, 9, FALSE),"")="", "SIN RUBRO", VLOOKUP(A722, 'Base 3F'!$B:$J, 9, FALSE))) -> Construcción | D722: acerosaceper@gmail.com | E722: Secundario | F722: funcional
A723: ACEROS COFER S.A. | B723: =IF(A723="", "", IF(IFERROR(VLOOKUP(A723, 'Base 3F'!$B:$C, 2, FALSE),"")="", "SIN CUIT", VLOOKUP(A723, 'Base 3F'!$B:$C, 2, FALSE))) -> 30707576444 | C723: =IF(A723="", "", IF(IFERROR(VLOOKUP(A723, 'Base 3F'!$B:$J, 9, FALSE),"")="", "SIN RUBRO", VLOOKUP(A723, 'Base 3F'!$B:$J, 9, FALSE))) -> Metalúrgica | D723: dante@aceroscofer.com.ar | E723: Secundario | F723: funcional
... A2320: 2G ADHESIVOS S.R.L. | B2320: =IF(A2320="", "", IF(IFERROR(VLOOKUP(A2320, 'Base 3F'!$B:$C, 2, FALSE),"")="", "SIN CUIT", VLOOKUP(A2320, 'Base 3F'!$B:$C, 2, FALSE))) -> 30714815179 | C2320: =IF(A2320="", "", IF(IFERROR(VLOOKUP(A2320, 'Base 3F'!$B:$J, 9, FALSE),"")="", "SIN RUBRO", VLOOKUP(A2320, 'Base 3F'!$B:$J, 9, FALSE))) -> Química | D2320: xxxxxxxxxxxxxxxxxxx@gmail.com | E2320: Principal | F2320: rebotado_bandeja_llena

Sheet Mapeo
A1: Rubro | B1: Cantidad | C1: % | E1: Localidad | F1: Cantidad | G1: %
A2: Agropecuaria | B2: =COUNTIF('Base 3F'!J5:J1964, A2) -> 6 | C2: =B2/B$35 -> 0.0033112583 | E2: Caseros | F2: =COUNTIF('Base 3F'!G5:G1964, E2) -> 813 | G2: =F2/F$18 -> 0.40207715
A3: Alimenticia | B3: =COUNTIF('Base 3F'!J5:J1964, A3) -> 113 | C3: =B3/B$35 -> 0.062362031 | E3: Churruca | F3: =COUNTIF('Base 3F'!G6:G1964, E3) -> 2 | G3: =F3/F$18 -> 0.00098911968
A4: Automotor | B4: =COUNTIF('Base 3F'!J5:J1964, A4) -> 14 | C4: =B4/B$35 -> 0.0077262693 | E4: Ciudad Jardín Lomas del Palomar | F4: =COUNTIF('Base 3F'!G7:G1964, E4) -> 16 | G4: =F4/F$18 -> 0.0079129575
A5: Bebidas | B5: =COUNTIF('Base 3F'!J5:J1964, A5) -> 18 | C5: =B5/B$35 -> 0.0099337748 | E5: Ciudadela | F5: =COUNTIF('Base 3F'!G7:G1964, E5) -> 483 | G5: =F5/F$18 -> 0.2388724
A6: Calzado | B6: =COUNTIF('Base 3F'!J5:J1964, A6) -> 33 | C6: =B6/B$35 -> 0.018211921 | E6: El Libertador | F6: =COUNTIF('Base 3F'!G8:G1964, E6) -> 0 | G6: =F6/F$18 -> 0
A7: Caucho | B7: =COUNTIF('Base 3F'!J5:J1964, A7) -> 19 | C7: =B7/B$35 -> 0.010485651 | E7: José Ingenieros | F7: =COUNTIF('Base 3F'!G9:G1964, E7) -> 61 | G7: =F7/F$18 -> 0.03016815
A8: Comercio | B8: =COUNTIF('Base 3F'!J5:J1964, A8) -> 1 | C8: =B8/B$35 -> 0.00055187638 | E8: Loma Hermosa | F8: =COUNTIF('Base 3F'!G10:G1964, E8) -> 235 | G8: =F8/F$18 -> 0.11622156
A9: Construcción | B9: =COUNTIF('Base 3F'!J5:J1964, A9) -> 80 | C9: =B9/B$35 -> 0.04415011 | E9: Martín Coronado | F9: =COUNTIF('Base 3F'!G11:G1964, E9) -> 31 | G9: =F9/F$18 -> 0.015331355
A10: Cosmética | B10: =COUNTIF('Base 3F'!J5:J1964, A10) -> 2 | C10: =B10/B$35 -> 0.0011037528 | E10: Once de Septiembre | F10: =COUNTIF('Base 3F'!G12:G1964, E10) -> 0 | G10: =F10/F$18 -> 0
A11: Cuero | B11: =COUNTIF('Base 3F'!J5:J1964, A11) -> 5 | C11: =B11/B$35 -> 0.0027593819 | E11: Pablo Podestá | F11: =COUNTIF('Base 3F'!G13:G1964, E11) -> 67 | G11: =F11/F$18 -> 0.033135509
A12: Electricidad | B12: =COUNTIF('Base 3F'!J5:J1964, A12) -> 4 | C12: =B12/B$35 -> 0.0022075055 | E12: Remedios de Escalada | F12: =COUNTIF('Base 3F'!G14:G1964, E12) -> 0 | G12: =F12/F$18 -> 0
A13: Electrónica | B13: =COUNTIF('Base 3F'!J5:J1964, A13) -> 67 | C13: =B13/B$35 -> 0.036975717 | E13: Sáenz Peña | F13: =COUNTIF('Base 3F'!G15:G1964, E13) -> 49 | G13: =F13/F$18 -> 0.024233432
A14: Gráfica | B14: =COUNTIF('Base 3F'!J5:J1964, A14) -> 29 | C14: =B14/B$35 -> 0.016004415 | E14: Santos Lugares | F14: =COUNTIF('Base 3F'!G16:G1964, E14) -> 65 | G14: =F14/F$18 -> 0.03214639
A15: Industria | B15: =COUNTIF('Base 3F'!J5:J1964, A15) -> 25 | C15: =B15/B$35 -> 0.013796909 | E15: Villa Bosch | F15: =COUNTIF('Base 3F'!G17:G1964, E15) -> 113 | G15: =F15/F$18 -> 0.055885262
A16: Informática | B16: =COUNTIF('Base 3F'!J5:J1964, A16) -> 4 | C16: =B16/B$35 -> 0.0022075055 | E16: Villa Raffo | F16: =COUNTIF('Base 3F'!G18:G1964, E16) -> 20 | G16: =F16/F$18 -> 0.0098911968
A17: Logística | B17: =COUNTIF('Base 3F'!J5:J1964, A17) -> 1 | C17: =B17/B$35 -> 0.00055187638 | E17: Fuera de 3F | F17: 67 | G17: =F17/F$18 -> 0.033135509
A18: Madera | B18: =COUNTIF('Base 3F'!J5:J1964, A18) -> 114 | C18: =B18/B$35 -> 0.062913907 | E18: TOTALES | F18: =SUM(F2:F17) -> 2022 | G18: =SUM(G2:G17) -> 1
A19: Manufactura | B19: =COUNTIF('Base 3F'!J5:J1964, A19) -> 16 | C19: =B19/B$35 -> 0.0088300221
A20: Metalmecánica | B20: =COUNTIF('Base 3F'!J5:J1964, A20) -> 80 | C20: =B20/B$35 -> 0.04415011
A21: Metalúrgica | B21: =COUNTIF('Base 3F'!J5:J1964, A21) -> 637 | C21: =B21/B$35 -> 0.35154525
A22: Minería | B22: =COUNTIF('Base 3F'!J5:J1964, A22) -> 1 | C22: =B22/B$35 -> 0.00055187638
A23: Olivicola | B23: =COUNTIF('Base 3F'!J5:J1964, A23) -> 1 | C23: =B23/B$35 -> 0.00055187638
A24: Orfebrería | B24: =COUNTIF('Base 3F'!J5:J1964, A24) -> 2 | C24: =B24/B$35 -> 0.0011037528
A25: Papel | B25: =COUNTIF('Base 3F'!J5:J1964, A25) -> 47 | C25: =B25/B$35 -> 0.02593819
A26: Petróleo | B26: =COUNTIF('Base 3F'!J5:J1964, A26) -> 1 | C26: =B26/B$35 -> 0.00055187638
A27: Piedra | B27: =COUNTIF('Base 3F'!J5:J1964, A27) -> 3 | C27: =B27/B$35 -> 0.0016556291
A28: Plástico | B28: =COUNTIF('Base 3F'!J5:J1964, A28) -> 0 | C28: =B28/B$35 -> 0
A29: Publicidad | B29: =COUNTIF('Base 3F'!J5:J1964, A29) -> 1 | C29: =B29/B$35 -> 0.00055187638
A30: Servicios | B30: =COUNTIF('Base 3F'!J5:J1964, A30) -> 241 | C30: =B30/B$35 -> 0.13300221
A31: Química | B31: =COUNTIF('Base 3F'!J5:J1964, A31) -> 90 | C31: =B31/B$35 -> 0.049668874
A32: Textil | B32: =COUNTIF('Base 3F'!J5:J1964, A32) -> 146 | C32: =B32/B$35 -> 0.080573951
A33: Vidrio | B33: =COUNTIF('Base 3F'!J5:J1964, A33) -> 9 | C33: =B33/B$35 -> 0.0049668874
A34: Otros | B34: =COUNTIF('Base 3F'!J5:J1964, "=-") -> 2 | C34: =B34/B$35 -> 0.0011037528
A35: TOTALES | B35: =SUM(B2:B34) -> 1812 | C35: =SUM(C2:C34) -> 1

Sheet Contacto 1 y 2 (a eliminar)
A1: CONTACTO 1 | B1: 746 mails
A3: angelina@estudioapop.com.ar
A4: lgreco@amasd.com.ar
A5: liliappardo@yahoo.com.ar
A6: juancluna@aceroscofer.com.ar
A7: info@acerosalvear.com
A8: graciela@inoxicaseros.com.ar
A9: vholub@acerosmb.com.ar
A10: holubvictor@gmail.com
A11: dachilli@los-amores.com.ar
A12: gerencia@aditivosplasticos.com
A13: gafonso@soluplex.com
A14: eduardo@agmetalurgica.com.ar
... A757: gmartin@valke.com.ar
A758: arredamentosbosch@hotmail.com | B758: Nuevos contacto 1
A759: info@mis-plast.com.ar
A760: fabfit@hotmail.com
A761: malmebsrl@outlook.com
A762: admmieleselchaltensrl@gmail.com
A763: fernando@wiremac.com.ar
A764: procesadorajeans@gmail.com
A765: profilesaceros@gmail.com
A766: mgraviotto@burkool.com.ar
A767: info@maferbul.com.ar
A768: martingabrielluna@yahoo.com
A769: corradiniremaches@gmail.com
A770: hcorraremaches@gmail.com
A771: corradiniricardov@gmail.com
B773: Contacto 2

Sheet Mails A(a eliminar)
A1: mails A | C1: 522 mails
A2: angelina@estudioapop.com.ar
A3: lgreco@amasd.com.ar
A4: liliappardo@yahoo.com.ar
A5: juancluna@aceroscofer.com.ar
A6: info@acerosalvear.com
A7: graciela@inoxicaseros.com.ar
A8: vholub@acerosmb.com.ar
A9: holubvictor@gmail.com
A10: gerencia@aditivosplasticos.com
A11: gafonso@soluplex.com
A12: eduardo@agmetalurgica.com.ar
A13: r-roussilian@aiman-sa.com
... A531: gasamed@hotmail.com
